{
  "type": "Feature",
  "properties": {
    "gn:admin1_code":"04",
    "gn:asciiname":"Norobanta Fula",
    "gn:cc2":"GW",
    "gn:country_code":"GW",
    "gn:dem":18,
    "gn:feature_class":"P",
    "gn:feature_code":"PPL",
    "gn:name":"Norobanta Fula",
    "gn:population":0,
    "gn:timezone":"Africa/Bissau",
    "iso:country":"GW",
    "name:und_x_variant":[
        "Norobantam",
        "Norobanta Fula"
    ],
    "wof:name":"Norobanta Fula",
    "wof:placetype":"locality"
},
  "geometry": {"coordinates":[-15.05278,12.61722],"type":"Point"}
}