{
  "type": "Feature",
  "properties": {
    "gn:admin1_code":"04",
    "gn:asciiname":"Gendo",
    "gn:cc2":"GW",
    "gn:country_code":"GW",
    "gn:dem":28,
    "gn:feature_class":"P",
    "gn:feature_code":"PPL",
    "gn:name":"Gendo",
    "gn:population":0,
    "gn:timezone":"Africa/Bissau",
    "iso:country":"GW",
    "name:und_x_variant":[
        "Gindu",
        "Gendo"
    ],
    "wof:name":"Gendo",
    "wof:placetype":"locality"
},
  "geometry": {"coordinates":[-15.02,12.40306],"type":"Point"}
}