{
  "type": "Feature",
  "properties": {
    "gn:admin1_code":"04",
    "gn:asciiname":"Forol",
    "gn:cc2":"GW",
    "gn:country_code":"GW",
    "gn:dem":25,
    "gn:feature_class":"P",
    "gn:feature_code":"PPL",
    "gn:name":"Forol",
    "gn:population":0,
    "gn:timezone":"Africa/Bissau",
    "iso:country":"GW",
    "name:und_x_variant":[
        "Farol",
        "Forol"
    ],
    "wof:name":"Forol",
    "wof:placetype":"locality"
},
  "geometry": {"coordinates":[-15.50917,12.37611],"type":"Point"}
}