{
  "type": "Feature",
  "properties": {
    "gn:admin1_code":"04",
    "gn:asciiname":"Bissum",
    "gn:country_code":"GW",
    "gn:dem":25,
    "gn:feature_class":"P",
    "gn:feature_code":"PPL",
    "gn:name":"Bissum",
    "gn:population":0,
    "gn:timezone":"Africa/Bissau",
    "iso:country":"GW",
    "wof:name":"Bissum",
    "wof:placetype":"locality"
},
  "geometry": {"coordinates":[-15.66583,12.24056],"type":"Point"}
}