{
  "type": "Feature",
  "properties": {
    "gn:admin1_code":"00",
    "gn:asciiname":"Sincha Coi",
    "gn:country_code":"GW",
    "gn:dem":64,
    "gn:feature_class":"P",
    "gn:feature_code":"PPL",
    "gn:name":"Sinch\u00e3 Coi",
    "gn:population":0,
    "gn:timezone":"Africa/Bissau",
    "iso:country":"GW",
    "wof:name":"Sincha Coi",
    "wof:placetype":"locality"
},
  "geometry": {"coordinates":[-14.13333,12.33333],"type":"Point"}
}