{
  "type": "Feature",
  "properties": {
    "gn:admin1_code":"04",
    "gn:asciiname":"Olossato",
    "gn:cc2":"GW",
    "gn:country_code":"GW",
    "gn:dem":4,
    "gn:feature_class":"P",
    "gn:feature_code":"PPL",
    "gn:name":"Olossato",
    "gn:population":0,
    "gn:timezone":"Africa/Bissau",
    "iso:country":"GW",
    "name:und_x_variant":[
        "Olossate",
        "Olossato"
    ],
    "wof:name":"Olossato",
    "wof:placetype":"locality"
},
  "geometry": {"coordinates":[-15.32861,12.31972],"type":"Point"}
}