{
  "type": "Feature",
  "properties": {
    "gn:admin1_code":"00",
    "gn:asciiname":"Canjai Fula",
    "gn:country_code":"GW",
    "gn:dem":35,
    "gn:feature_class":"P",
    "gn:feature_code":"PPL",
    "gn:name":"Canjai Fula",
    "gn:population":0,
    "gn:timezone":"Africa/Bissau",
    "iso:country":"GW",
    "wof:name":"Canjai Fula",
    "wof:placetype":"locality"
},
  "geometry": {"coordinates":[-14.65,12.36667],"type":"Point"}
}