{
  "type": "Feature",
  "properties": {
    "gn:admin1_code":"06",
    "gn:asciiname":"Basseor",
    "gn:cc2":"GW",
    "gn:country_code":"GW",
    "gn:dem":22,
    "gn:feature_class":"P",
    "gn:feature_code":"PPL",
    "gn:name":"Basseor",
    "gn:population":0,
    "gn:timezone":"Africa/Bissau",
    "iso:country":"GW",
    "name:und_x_variant":[
        "Bassear",
        "Basseo",
        "Basseor"
    ],
    "wof:name":"Basseor",
    "wof:placetype":"locality"
},
  "geometry": {"coordinates":[-16.60667,12.33861],"type":"Point"}
}