{
  "type": "Feature",
  "properties": {
    "gn:admin1_code":"00",
    "gn:asciiname":"Cansoco Mandinga",
    "gn:country_code":"GW",
    "gn:dem":16,
    "gn:feature_class":"P",
    "gn:feature_code":"PPL",
    "gn:name":"Cansoc\u00f3 Mandinga",
    "gn:population":0,
    "gn:timezone":"Africa/Bissau",
    "iso:country":"GW",
    "wof:name":"Cansoco Mandinga",
    "wof:placetype":"locality"
},
  "geometry": {"coordinates":[-15.36667,12.33333],"type":"Point"}
}