{
  "type": "Feature",
  "properties": {
    "gn:admin1_code":"00",
    "gn:asciiname":"Sibicroto",
    "gn:cc2":"GW",
    "gn:country_code":"GW",
    "gn:dem":13,
    "gn:feature_class":"P",
    "gn:feature_code":"PPL",
    "gn:name":"Sibicroto",
    "gn:population":0,
    "gn:timezone":"Africa/Bissau",
    "iso:country":"GW",
    "name:und_x_variant":[
        "Sibicruato",
        "Sinch\u00e3 Fodengali",
        "Sibicroto"
    ],
    "wof:name":"Sibicroto",
    "wof:placetype":"locality"
},
  "geometry": {"coordinates":[-14.86667,12.01667],"type":"Point"}
}