{
  "type": "Feature",
  "properties": {
    "gn:admin1_code":"00",
    "gn:asciiname":"Beliege",
    "gn:cc2":"GW",
    "gn:country_code":"GW",
    "gn:dem":17,
    "gn:feature_class":"P",
    "gn:feature_code":"PPL",
    "gn:name":"Beliege",
    "gn:population":0,
    "gn:timezone":"Africa/Bissau",
    "iso:country":"GW",
    "name:und_x_variant":[
        "Belieje",
        "Beliege"
    ],
    "wof:name":"Beliege",
    "wof:placetype":"locality"
},
  "geometry": {"coordinates":[-16.01667,11.95],"type":"Point"}
}