{
  "type": "Feature",
  "properties": {
    "gn:admin1_code":"00",
    "gn:asciiname":"Bapeja",
    "gn:country_code":"GW",
    "gn:dem":33,
    "gn:feature_class":"P",
    "gn:feature_code":"PPL",
    "gn:name":"Bapeja",
    "gn:population":0,
    "gn:timezone":"Africa/Bissau",
    "iso:country":"GW",
    "wof:name":"Bapeja",
    "wof:placetype":"locality"
},
  "geometry": {"coordinates":[-16.11667000000001,12.21667],"type":"Point"}
}