{
  "type": "Feature",
  "properties": {
    "gn:admin1_code":"00",
    "gn:asciiname":"Badancar",
    "gn:country_code":"GW",
    "gn:dem":27,
    "gn:feature_class":"P",
    "gn:feature_code":"PPL",
    "gn:name":"Badancar",
    "gn:population":0,
    "gn:timezone":"Africa/Bissau",
    "iso:country":"GW",
    "wof:name":"Badancar",
    "wof:placetype":"locality"
},
  "geometry": {"coordinates":[-15.33333,12.56667],"type":"Point"}
}