{
  "type": "Feature",
  "properties": {
    "gn:admin1_code":"00",
    "gn:asciiname":"Nhanaia",
    "gn:country_code":"GW",
    "gn:dem":10,
    "gn:feature_class":"P",
    "gn:feature_code":"PPL",
    "gn:name":"Nhanai\u00e0",
    "gn:population":0,
    "gn:timezone":"Africa/Bissau",
    "iso:country":"GW",
    "wof:name":"Nhanaia",
    "wof:placetype":"locality"
},
  "geometry": {"coordinates":[-15.51667,12.41667],"type":"Point"}
}