{
  "type": "Feature",
  "properties": {
    "gn:admin1_code":"00",
    "gn:asciiname":"Nhantampa",
    "gn:country_code":"GW",
    "gn:dem":56,
    "gn:feature_class":"P",
    "gn:feature_code":"PPL",
    "gn:name":"Nhantampa",
    "gn:population":0,
    "gn:timezone":"Africa/Bissau",
    "iso:country":"GW",
    "wof:name":"Nhantampa",
    "wof:placetype":"locality"
},
  "geometry": {"coordinates":[-14.46667,12.28333],"type":"Point"}
}