{
  "type": "Feature",
  "properties": {
    "gn:admin1_code":"00",
    "gn:asciiname":"Farancunda Balanta",
    "gn:cc2":"GW",
    "gn:country_code":"GW",
    "gn:dem":9,
    "gn:feature_class":"P",
    "gn:feature_code":"PPL",
    "gn:name":"Farancunda Balanta",
    "gn:population":0,
    "gn:timezone":"Africa/Bissau",
    "iso:country":"GW",
    "name:und_x_variant":[
        "Umhol",
        "Farancunda Balanta"
    ],
    "wof:name":"Farancunda Balanta",
    "wof:placetype":"locality"
},
  "geometry": {"coordinates":[-15.18333,11.51667],"type":"Point"}
}