{
  "type": "Feature",
  "properties": {
    "gn:admin1_code":"04",
    "gn:asciiname":"Cufeu",
    "gn:country_code":"GW",
    "gn:dem":30,
    "gn:feature_class":"P",
    "gn:feature_code":"PPL",
    "gn:name":"Cufeu",
    "gn:population":0,
    "gn:timezone":"Africa/Bissau",
    "iso:country":"GW",
    "wof:name":"Cufeu",
    "wof:placetype":"locality"
},
  "geometry": {"coordinates":[-15.38417,12.49472],"type":"Point"}
}