{
  "type": "Feature",
  "properties": {
    "gn:admin1_code":"00",
    "gn:asciiname":"Sincha Jai",
    "gn:country_code":"GW",
    "gn:dem":20,
    "gn:feature_class":"P",
    "gn:feature_code":"PPL",
    "gn:name":"Sinch\u00e3 Jai",
    "gn:population":0,
    "gn:timezone":"Africa/Bissau",
    "iso:country":"GW",
    "wof:name":"Sincha Jai",
    "wof:placetype":"locality"
},
  "geometry": {"coordinates":[-14.81667,12.25],"type":"Point"}
}