{
  "type": "Feature",
  "properties": {
    "gn:admin1_code":"00",
    "gn:asciiname":"Sare Budi",
    "gn:cc2":"GW",
    "gn:country_code":"GW",
    "gn:dem":21,
    "gn:feature_class":"P",
    "gn:feature_code":"PPL",
    "gn:name":"Sare Budi",
    "gn:population":0,
    "gn:timezone":"Africa/Bissau",
    "iso:country":"GW",
    "name:und_x_variant":[
        "Sare Bode",
        "Sare Budi"
    ],
    "wof:name":"Sare Budi",
    "wof:placetype":"locality"
},
  "geometry": {"coordinates":[-14.83333,12.23333],"type":"Point"}
}