{
  "type": "Feature",
  "properties": {
    "gn:admin1_code":"00",
    "gn:asciiname":"Gentilame",
    "gn:cc2":"GW",
    "gn:country_code":"GW",
    "gn:dem":17,
    "gn:feature_class":"P",
    "gn:feature_code":"PPL",
    "gn:name":"Gentilame",
    "gn:population":0,
    "gn:timezone":"Africa/Bissau",
    "iso:country":"GW",
    "name:und_x_variant":[
        "Sant\u00e3o",
        "Gentilame"
    ],
    "wof:name":"Gentilame",
    "wof:placetype":"locality"
},
  "geometry": {"coordinates":[-15.06667,11.86667],"type":"Point"}
}