{
  "type": "Feature",
  "properties": {
    "gn:admin1_code":"04",
    "gn:asciiname":"Burume",
    "gn:cc2":"GW",
    "gn:country_code":"GW",
    "gn:dem":22,
    "gn:feature_class":"P",
    "gn:feature_code":"PPL",
    "gn:name":"Burume",
    "gn:population":0,
    "gn:timezone":"Africa/Bissau",
    "iso:country":"GW",
    "name:und_x_variant":[
        "Burame",
        "Burume"
    ],
    "wof:name":"Burume",
    "wof:placetype":"locality"
},
  "geometry": {"coordinates":[-15.70694,12.22972],"type":"Point"}
}