{
  "type": "Feature",
  "properties": {
    "gn:admin1_code":"06",
    "gn:asciiname":"Cassalol",
    "gn:cc2":"GW",
    "gn:country_code":"GW",
    "gn:dem":16,
    "gn:feature_class":"P",
    "gn:feature_code":"PPL",
    "gn:name":"Cassalol",
    "gn:population":0,
    "gn:timezone":"Africa/Bissau",
    "iso:country":"GW",
    "name:und_x_variant":[
        "Cassolol",
        "Cassalol"
    ],
    "wof:name":"Cassalol",
    "wof:placetype":"locality"
},
  "geometry": {"coordinates":[-16.54778,12.32528],"type":"Point"}
}