{
  "type": "Feature",
  "properties": {
    "gn:admin1_code":"00",
    "gn:asciiname":"Funsonfo",
    "gn:country_code":"GW",
    "gn:dem":5,
    "gn:feature_class":"P",
    "gn:feature_code":"PPL",
    "gn:name":"Funsonfo",
    "gn:population":0,
    "gn:timezone":"Africa/Bissau",
    "iso:country":"GW",
    "wof:name":"Funsonfo",
    "wof:placetype":"locality"
},
  "geometry": {"coordinates":[-15.31667,11.15],"type":"Point"}
}