{
  "type": "Feature",
  "properties": {
    "iso:country":"GW",
    "name:ast_x_preferred":[
        "Bissor\u00e3"
    ],
    "name:cat_x_preferred":[
        "Bissor\u00e3"
    ],
    "name:ceb_x_preferred":[
        "Bissor\u00e3"
    ],
    "name:deu_x_preferred":[
        "Bissor\u00e3"
    ],
    "name:eng_x_preferred":[
        "Bissor\u00e3"
    ],
    "name:fin_x_preferred":[
        "Bissor\u00e3"
    ],
    "name:fra_x_preferred":[
        "Bissor\u00e3"
    ],
    "name:glg_x_preferred":[
        "Bissor\u00e3"
    ],
    "name:ita_x_preferred":[
        "Bissor\u00e3"
    ],
    "name:jpn_x_preferred":[
        "\u30d3\u30bd\u30e9\u30f3"
    ],
    "name:kor_x_preferred":[
        "\ube44\uc18c\ub791"
    ],
    "name:lit_x_preferred":[
        "Bisora"
    ],
    "name:nld_x_preferred":[
        "Bissor\u00e3"
    ],
    "name:pol_x_preferred":[
        "Bissora"
    ],
    "name:por_x_preferred":[
        "Bissor\u00e3"
    ],
    "name:ron_x_preferred":[
        "Bissor\u00e3"
    ],
    "name:rus_x_preferred":[
        "\u0411\u0438\u0441\u043e\u0440\u0430\u043d"
    ],
    "name:rus_x_variant":[
        "\u0411\u0438\u0441\u043e\u0440\u0430"
    ],
    "name:swe_x_preferred":[
        "Bissor\u00e3"
    ],
    "name:und_x_variant":[
        "Bissoram"
    ],
    "name:urd_x_preferred":[
        "\u0628\u06cc\u0633\u0648\u0631\u0627"
    ],
    "name:zho_x_preferred":[
        "\u6bd4\u7d22\u6717"
    ],
    "qs:gn_country":"GW",
    "qs:gn_fcode":"PPLA",
    "qs:gn_pop":12688,
    "qs:name":"Bissor\u00e3",
    "qs:name_adm0":"Guin\u00e9-Bissau",
    "qs:name_adm1":"Oio",
    "qs:photos":0,
    "qs:photos_1k":0,
    "qs:photos_9k":0,
    "qs:photos_9r":0,
    "qs:photos_all":0,
    "qs:photos_sr":0,
    "qs:placetype":"Town",
    "qs:pop_sr":"6",
    "qs:woe_adm0":23424929,
    "wd:wordcount":137,
    "wof:name":"Bissor\u00e3",
    "wof:placetype":"locality",
    "wof:population":12688
},
  "geometry": {"coordinates":[-15.4475,12.22306],"type":"Point"}
}