{
  "type": "Feature",
  "properties": {
    "gn:admin1_code":"00",
    "gn:asciiname":"Sare Dabel",
    "gn:country_code":"GW",
    "gn:dem":38,
    "gn:feature_class":"P",
    "gn:feature_code":"PPL",
    "gn:name":"Sare Dabel",
    "gn:population":0,
    "gn:timezone":"Africa/Bissau",
    "iso:country":"GW",
    "wof:name":"Sare Dabel",
    "wof:placetype":"locality"
},
  "geometry": {"coordinates":[-14.56667,12.46667],"type":"Point"}
}