{
  "type": "Feature",
  "properties": {
    "gn:admin1_code":"00",
    "gn:asciiname":"Ponta Inacia",
    "gn:country_code":"GW",
    "gn:dem":23,
    "gn:feature_class":"P",
    "gn:feature_code":"PPL",
    "gn:name":"Ponta In\u00e1cia",
    "gn:population":0,
    "gn:timezone":"Africa/Bissau",
    "iso:country":"GW",
    "wof:name":"Ponta Inacia",
    "wof:placetype":"locality"
},
  "geometry": {"coordinates":[-15.13333,12.41667],"type":"Point"}
}