{
  "type": "Feature",
  "properties": {
    "gn:admin1_code":"00",
    "gn:asciiname":"Ieroiel",
    "gn:country_code":"GW",
    "gn:dem":47,
    "gn:feature_class":"P",
    "gn:feature_code":"PPL",
    "gn:name":"Ieroiel",
    "gn:population":0,
    "gn:timezone":"Africa/Bissau",
    "iso:country":"GW",
    "wof:name":"Ieroiel",
    "wof:placetype":"locality"
},
  "geometry": {"coordinates":[-14.85,11.53333],"type":"Point"}
}