{
  "type": "Feature",
  "properties": {
    "gn:admin1_code":"00",
    "gn:asciiname":"Ga Chiquinho Mancanha",
    "gn:country_code":"GW",
    "gn:dem":16,
    "gn:feature_class":"P",
    "gn:feature_code":"PPL",
    "gn:name":"G\u00e3 Chiquinho Mancanha",
    "gn:population":0,
    "gn:timezone":"Africa/Bissau",
    "iso:country":"GW",
    "wof:name":"Ga Chiquinho Mancanha",
    "wof:placetype":"locality"
},
  "geometry": {"coordinates":[-15.26667,11.85],"type":"Point"}
}