{
  "type": "Feature",
  "properties": {
    "gn:admin1_code":"00",
    "gn:asciiname":"Sare Queda",
    "gn:cc2":"GW",
    "gn:country_code":"GW",
    "gn:dem":32,
    "gn:feature_class":"P",
    "gn:feature_code":"PPL",
    "gn:name":"Sare Queda",
    "gn:population":0,
    "gn:timezone":"Africa/Bissau",
    "iso:country":"GW",
    "name:und_x_variant":[
        "Sare Queta",
        "Sare Queda"
    ],
    "wof:name":"Sare Queda",
    "wof:placetype":"locality"
},
  "geometry": {"coordinates":[-14.93333,12.61667],"type":"Point"}
}