{
  "type": "Feature",
  "properties": {
    "gn:admin1_code":"00",
    "gn:asciiname":"Cafia",
    "gn:cc2":"GW",
    "gn:country_code":"GW",
    "gn:dem":38,
    "gn:feature_class":"P",
    "gn:feature_code":"PPL",
    "gn:name":"Cafi\u00e0",
    "gn:population":0,
    "gn:timezone":"Africa/Bissau",
    "iso:country":"GW",
    "name:und_x_variant":[
        "Cuf\u00eda",
        "Cafi\u00e0"
    ],
    "wof:name":"Cafia",
    "wof:placetype":"locality"
},
  "geometry": {"coordinates":[-14.85,12.18333],"type":"Point"}
}