{
  "type": "Feature",
  "properties": {
    "gn:admin1_code":"00",
    "gn:asciiname":"Banim",
    "gn:cc2":"GW",
    "gn:country_code":"GW",
    "gn:dem":9,
    "gn:feature_class":"P",
    "gn:feature_code":"PPL",
    "gn:name":"Banim",
    "gn:population":0,
    "gn:timezone":"Africa/Bissau",
    "iso:country":"GW",
    "name:und_x_variant":[
        "Bane",
        "Banim"
    ],
    "wof:name":"Banim",
    "wof:placetype":"locality"
},
  "geometry": {"coordinates":[-15.23333,12.48333],"type":"Point"}
}