{
  "type": "Feature",
  "properties": {
    "gn:admin1_code":"06",
    "gn:asciiname":"Ingorezinho",
    "gn:country_code":"GW",
    "gn:dem":21,
    "gn:feature_class":"P",
    "gn:feature_code":"PPL",
    "gn:name":"Ingor\u00e8zinho",
    "gn:population":0,
    "gn:timezone":"Africa/Bissau",
    "iso:country":"GW",
    "wof:name":"Ingorezinho",
    "wof:placetype":"locality"
},
  "geometry": {"coordinates":[-15.79083,12.42778],"type":"Point"}
}