{
  "type": "Feature",
  "properties": {
    "gn:admin1_code":"00",
    "gn:asciiname":"Ganfode Jassi",
    "gn:country_code":"GW",
    "gn:dem":10,
    "gn:feature_class":"P",
    "gn:feature_code":"PPL",
    "gn:name":"Ganfod\u00e8 Jassi",
    "gn:population":0,
    "gn:timezone":"Africa/Bissau",
    "iso:country":"GW",
    "wof:name":"Ganfode Jassi",
    "wof:placetype":"locality"
},
  "geometry": {"coordinates":[-15.36667,11.65],"type":"Point"}
}