{
  "type": "Feature",
  "properties": {
    "gn:admin1_code":"06",
    "gn:asciiname":"Blansar",
    "gn:country_code":"GW",
    "gn:dem":18,
    "gn:feature_class":"P",
    "gn:feature_code":"PPL",
    "gn:name":"Blansar",
    "gn:population":0,
    "gn:timezone":"Africa/Bissau",
    "iso:country":"GW",
    "wof:name":"Blansar",
    "wof:placetype":"locality"
},
  "geometry": {"coordinates":[-15.77028,12.32944],"type":"Point"}
}