{
  "type": "Feature",
  "properties": {
    "gn:admin1_code":"00",
    "gn:asciiname":"Sincha Quecuta",
    "gn:country_code":"GW",
    "gn:dem":43,
    "gn:feature_class":"P",
    "gn:feature_code":"PPL",
    "gn:name":"Sinch\u00e3 Quecuta",
    "gn:population":0,
    "gn:timezone":"Africa/Bissau",
    "iso:country":"GW",
    "wof:name":"Sincha Quecuta",
    "wof:placetype":"locality"
},
  "geometry": {"coordinates":[-14.46667,12.41667],"type":"Point"}
}