{
  "type": "Feature",
  "properties": {
    "gn:admin1_code":"00",
    "gn:asciiname":"Cansamba",
    "gn:cc2":"GW",
    "gn:country_code":"GW",
    "gn:dem":66,
    "gn:feature_class":"P",
    "gn:feature_code":"PPL",
    "gn:name":"Cansamba",
    "gn:population":0,
    "gn:timezone":"Africa/Bissau",
    "iso:country":"GW",
    "name:und_x_variant":[
        "Cam Samba",
        "Cansamba"
    ],
    "wof:name":"Cansamba",
    "wof:placetype":"locality"
},
  "geometry": {"coordinates":[-14.21667,12.03333],"type":"Point"}
}