{
  "type": "Feature",
  "properties": {
    "gn:admin1_code":"04",
    "gn:asciiname":"Bolumbato",
    "gn:country_code":"GW",
    "gn:dem":32,
    "gn:feature_class":"P",
    "gn:feature_code":"PPL",
    "gn:name":"Bolumbato",
    "gn:population":0,
    "gn:timezone":"Africa/Bissau",
    "iso:country":"GW",
    "wof:name":"Bolumbato",
    "wof:placetype":"locality"
},
  "geometry": {"coordinates":[-15.17917,12.52139],"type":"Point"}
}