{
  "type": "Feature",
  "properties": {
    "gn:admin1_code":"00",
    "gn:asciiname":"Tubacuta",
    "gn:cc2":"GW",
    "gn:country_code":"GW",
    "gn:dem":22,
    "gn:feature_class":"P",
    "gn:feature_code":"PPL",
    "gn:name":"Tub\u00e1cut\u00e0",
    "gn:population":0,
    "gn:timezone":"Africa/Bissau",
    "iso:country":"GW",
    "name:und_x_variant":[
        "Tobacuta",
        "Tub\u00e1cut\u00e0"
    ],
    "wof:name":"Tubacuta",
    "wof:placetype":"locality"
},
  "geometry": {"coordinates":[-14.98333,11.83333],"type":"Point"}
}