{
  "type": "Feature",
  "properties": {
    "gn:admin1_code":"00",
    "gn:asciiname":"Tanta Cosse Samba",
    "gn:country_code":"GW",
    "gn:dem":36,
    "gn:feature_class":"P",
    "gn:feature_code":"PPL",
    "gn:name":"Tant\u00e3 Coss\u00e9 Samba",
    "gn:population":0,
    "gn:timezone":"Africa/Bissau",
    "iso:country":"GW",
    "wof:name":"Tanta Cosse Samba",
    "wof:placetype":"locality"
},
  "geometry": {"coordinates":[-14.55,12.26667],"type":"Point"}
}