{
  "type": "Feature",
  "properties": {
    "gn:admin1_code":"06",
    "gn:asciiname":"Untabualo",
    "gn:cc2":"GW",
    "gn:country_code":"GW",
    "gn:dem":29,
    "gn:feature_class":"P",
    "gn:feature_code":"PPL",
    "gn:name":"Untabualo",
    "gn:population":0,
    "gn:timezone":"Africa/Bissau",
    "iso:country":"GW",
    "name:und_x_variant":[
        "Bolanha",
        "Untabualo"
    ],
    "wof:name":"Untabualo",
    "wof:placetype":"locality"
},
  "geometry": {"coordinates":[-16.03528,12.43083],"type":"Point"}
}