{
  "type": "Feature",
  "properties": {
    "gn:admin1_code":"00",
    "gn:asciiname":"Carbanol",
    "gn:country_code":"GW",
    "gn:dem":33,
    "gn:feature_class":"P",
    "gn:feature_code":"PPL",
    "gn:name":"Carbanol",
    "gn:population":0,
    "gn:timezone":"Africa/Bissau",
    "iso:country":"GW",
    "wof:name":"Carbanol",
    "wof:placetype":"locality"
},
  "geometry": {"coordinates":[-14.78333,12.23333],"type":"Point"}
}