{
  "type": "Feature",
  "properties": {
    "gn:admin1_code":"00",
    "gn:asciiname":"Demba Taco",
    "gn:country_code":"GW",
    "gn:dem":36,
    "gn:feature_class":"P",
    "gn:feature_code":"PPL",
    "gn:name":"Demba Tac\u00f2",
    "gn:population":0,
    "gn:timezone":"Africa/Bissau",
    "iso:country":"GW",
    "wof:name":"Demba Taco",
    "wof:placetype":"locality"
},
  "geometry": {"coordinates":[-14.85,11.95],"type":"Point"}
}