{
  "type": "Feature",
  "properties": {
    "gn:admin1_code":"04",
    "gn:asciiname":"Binar",
    "gn:country_code":"GW",
    "gn:dem":33,
    "gn:feature_class":"P",
    "gn:feature_code":"PPL",
    "gn:name":"Binar",
    "gn:population":0,
    "gn:timezone":"Africa/Bissau",
    "iso:country":"GW",
    "wof:name":"Binar",
    "wof:placetype":"locality"
},
  "geometry": {"coordinates":[-15.32056,12.55806],"type":"Point"}
}