{
  "type": "Feature",
  "properties": {
    "gn:admin1_code":"00",
    "gn:asciiname":"Prabis",
    "gn:country_code":"GW",
    "gn:dem":23,
    "gn:feature_class":"P",
    "gn:feature_code":"PPL",
    "gn:name":"Pr\u00e1bis",
    "gn:population":0,
    "gn:timezone":"Africa/Bissau",
    "iso:country":"GW",
    "name:und_x_variant":[
        "Andr\u00e9",
        "Purabis",
        "Pr\u00e1bis"
    ],
    "wof:name":"Prabis",
    "wof:placetype":"locality"
},
  "geometry": {"coordinates":[-15.73889,11.8025],"type":"Point"}
}