{
  "type": "Feature",
  "properties": {
    "gn:admin1_code":"00",
    "gn:asciiname":"Prabis",
    "gn:country_code":"GW",
    "gn:dem":23,
    "gn:feature_class":"P",
    "gn:feature_code":"PPL",
    "gn:name":"Pr\u00e1bis",
    "gn:population":0,
    "gn:timezone":"Africa/Bissau",
    "iso:country":"GW",
    "name:cat_x_preferred":[
        "Prabis"
    ],
    "name:ceb_x_preferred":[
        "Prabis Sector"
    ],
    "name:deu_x_preferred":[
        "Prabis"
    ],
    "name:fin_x_preferred":[
        "Prabis"
    ],
    "name:fra_x_preferred":[
        "Prabis"
    ],
    "name:ita_x_preferred":[
        "Prabis"
    ],
    "name:jpn_x_preferred":[
        "\u30d7\u30e9\u30fc\u30d3\u30b9"
    ],
    "name:por_x_preferred":[
        "Prabis"
    ],
    "name:swe_x_preferred":[
        "Prabis Sector"
    ],
    "name:ukr_x_preferred":[
        "\u041f\u0440\u0430\u0431\u0456\u0441"
    ],
    "name:und_x_variant":[
        "Andr\u00e9",
        "Purabis",
        "Pr\u00e1bis"
    ],
    "wof:name":"Prabis",
    "wof:placetype":"locality"
},
  "geometry": {"coordinates":[-15.73889,11.8025],"type":"Point"}
}