{
  "type": "Feature",
  "properties": {
    "gn:admin1_code":"00",
    "gn:asciiname":"Bajefa",
    "gn:country_code":"GW",
    "gn:dem":69,
    "gn:feature_class":"P",
    "gn:feature_code":"PPL",
    "gn:name":"Bajefa",
    "gn:population":0,
    "gn:timezone":"Africa/Bissau",
    "iso:country":"GW",
    "wof:name":"Bajefa",
    "wof:placetype":"locality"
},
  "geometry": {"coordinates":[-14.25,12.41667],"type":"Point"}
}