{
  "type": "Feature",
  "properties": {
    "gn:admin1_code":"00",
    "gn:asciiname":"Nafo",
    "gn:country_code":"GW",
    "gn:dem":13,
    "gn:feature_class":"P",
    "gn:feature_code":"PPL",
    "gn:name":"Nafo",
    "gn:population":0,
    "gn:timezone":"Africa/Bissau",
    "iso:country":"GW",
    "name:azb_x_preferred":[
        "\u0646\u0627\u0641\u0648"
    ],
    "name:fas_x_preferred":[
        "\u0646\u0627\u0641\u0648"
    ],
    "name:fra_x_preferred":[
        "Nafo"
    ],
    "wof:name":"Nafo",
    "wof:placetype":"locality"
},
  "geometry": {"coordinates":[-15.08333,11.45],"type":"Point"}
}