{
  "type": "Feature",
  "properties": {
    "gn:admin1_code":"00",
    "gn:asciiname":"Ancadona",
    "gn:cc2":"GW",
    "gn:country_code":"GW",
    "gn:dem":9,
    "gn:feature_class":"P",
    "gn:feature_code":"PPL",
    "gn:name":"Ancadona",
    "gn:population":0,
    "gn:timezone":"Africa/Bissau",
    "iso:country":"GW",
    "name:und_x_variant":[
        "Caduna",
        "Ancadona"
    ],
    "wof:name":"Ancadona",
    "wof:placetype":"locality"
},
  "geometry": {"coordinates":[-16.18333,11.23333],"type":"Point"}
}