{
  "type": "Feature",
  "properties": {
    "gn:admin1_code":"00",
    "gn:asciiname":"Mil",
    "gn:country_code":"GW",
    "gn:dem":31,
    "gn:feature_class":"P",
    "gn:feature_code":"PPL",
    "gn:name":"Mil",
    "gn:population":0,
    "gn:timezone":"Africa/Bissau",
    "iso:country":"GW",
    "name:aze_x_preferred":[
        "Mil"
    ],
    "name:bre_x_preferred":[
        "Mil"
    ],
    "name:bul_x_preferred":[
        "MIL"
    ],
    "name:cat_x_preferred":[
        "Mil"
    ],
    "name:ceb_x_preferred":[
        "Mil"
    ],
    "name:deu_x_preferred":[
        "Mil"
    ],
    "name:fra_x_preferred":[
        "Mil"
    ],
    "name:glg_x_preferred":[
        "Mil"
    ],
    "name:heb_x_preferred":[
        "\u05de\u05d9\u05dc"
    ],
    "name:kat_x_preferred":[
        "\u10db\u10d8\u10da\u10d8"
    ],
    "name:nld_x_preferred":[
        "Mil"
    ],
    "name:nno_x_preferred":[
        "Mil"
    ],
    "name:pol_x_preferred":[
        "Mil"
    ],
    "name:rus_x_preferred":[
        "Mil"
    ],
    "name:spa_x_preferred":[
        "Mil"
    ],
    "name:tur_x_preferred":[
        "Mil"
    ],
    "name:ukr_x_preferred":[
        "Mil"
    ],
    "wof:name":"Mil",
    "wof:placetype":"locality"
},
  "geometry": {"coordinates":[-15.51667,12.23333],"type":"Point"}
}