{
  "type": "Feature",
  "properties": {
    "gn:admin1_code":"00",
    "gn:asciiname":"Mato de Cao",
    "gn:cc2":"GW",
    "gn:country_code":"GW",
    "gn:dem":10,
    "gn:feature_class":"P",
    "gn:feature_code":"PPL",
    "gn:name":"Mato de C\u00e3o",
    "gn:population":0,
    "gn:timezone":"Africa/Bissau",
    "iso:country":"GW",
    "name:und_x_variant":[
        "Mata do C\u00e3o",
        "Mato de C\u00e3o"
    ],
    "wof:name":"Mato de Cao",
    "wof:placetype":"locality"
},
  "geometry": {"coordinates":[-14.91667,12.05],"type":"Point"}
}