{
  "type": "Feature",
  "properties": {
    "gn:admin1_code":"00",
    "gn:asciiname":"Sincha Meta",
    "gn:country_code":"GW",
    "gn:dem":10,
    "gn:feature_class":"P",
    "gn:feature_code":"PPL",
    "gn:name":"Sinch\u00e3 Meta",
    "gn:population":0,
    "gn:timezone":"Africa/Bissau",
    "iso:country":"GW",
    "wof:name":"Sincha Meta",
    "wof:placetype":"locality"
},
  "geometry": {"coordinates":[-15.83333,12.23333],"type":"Point"}
}