{
  "type": "Feature",
  "properties": {
    "gn:admin1_code":"00",
    "gn:asciiname":"Jifim",
    "gn:cc2":"GW",
    "gn:country_code":"GW",
    "gn:dem":139,
    "gn:feature_class":"P",
    "gn:feature_code":"PPL",
    "gn:name":"Jifim",
    "gn:population":0,
    "gn:timezone":"Africa/Bissau",
    "iso:country":"GW",
    "name:und_x_variant":[
        "Lhifim",
        "Jifim"
    ],
    "wof:name":"Jifim",
    "wof:placetype":"locality"
},
  "geometry": {"coordinates":[-14.36667,11.78333],"type":"Point"}
}