{
  "type": "Feature",
  "properties": {
    "gn:admin1_code":"00",
    "gn:asciiname":"Tabadara",
    "gn:country_code":"GW",
    "gn:dem":76,
    "gn:feature_class":"P",
    "gn:feature_code":"PPL",
    "gn:name":"Tabadar\u00e1",
    "gn:population":0,
    "gn:timezone":"Africa/Bissau",
    "iso:country":"GW",
    "wof:name":"Tabadara",
    "wof:placetype":"locality"
},
  "geometry": {"coordinates":[-13.85,12.08333],"type":"Point"}
}