{
  "type": "Feature",
  "properties": {
    "gn:admin1_code":"04",
    "gn:asciiname":"Tambato Mandinga",
    "gn:cc2":"GW",
    "gn:country_code":"GW",
    "gn:dem":24,
    "gn:feature_class":"P",
    "gn:feature_code":"PPL",
    "gn:name":"Tambato Mandinga",
    "gn:population":0,
    "gn:timezone":"Africa/Bissau",
    "iso:country":"GW",
    "name:und_x_variant":[
        "Tambato",
        "Tambato Mandinga"
    ],
    "wof:name":"Tambato Mandinga",
    "wof:placetype":"locality"
},
  "geometry": {"coordinates":[-15.27667,12.42583],"type":"Point"}
}