{
  "type": "Feature",
  "properties": {
    "gn:admin1_code":"00",
    "gn:asciiname":"Demba",
    "gn:country_code":"GW",
    "gn:dem":49,
    "gn:feature_class":"P",
    "gn:feature_code":"PPL",
    "gn:name":"Demba",
    "gn:population":0,
    "gn:timezone":"Africa/Bissau",
    "iso:country":"GW",
    "name:ben_x_preferred":[
        "\u09a6\u09c7\u09ae\u09ac\u09be"
    ],
    "name:ceb_x_preferred":[
        "Demba"
    ],
    "name:deu_x_preferred":[
        "Demba"
    ],
    "name:ell_x_preferred":[
        "\u039d\u03c4\u03ad\u03bc\u03c0\u03b1"
    ],
    "name:fas_x_preferred":[
        "\u062f\u0645\u0628\u0627"
    ],
    "name:heb_x_preferred":[
        "\u05d3\u05de\u05d1\u05d4"
    ],
    "name:hin_x_preferred":[
        "\u0921\u0947\u0902\u092c\u093e"
    ],
    "name:hun_x_preferred":[
        "Demba"
    ],
    "name:ind_x_preferred":[
        "Demba"
    ],
    "name:ita_x_preferred":[
        "Demba"
    ],
    "name:kor_x_preferred":[
        "\ub380\ubc14"
    ],
    "name:pol_x_preferred":[
        "Demba"
    ],
    "name:ron_x_preferred":[
        "Demba"
    ],
    "name:rus_x_preferred":[
        "\u0414\u0435\u043c\u0431\u0430"
    ],
    "name:spa_x_preferred":[
        "Demba"
    ],
    "name:swe_x_preferred":[
        "Demba"
    ],
    "name:tur_x_preferred":[
        "Demba"
    ],
    "name:ukr_x_preferred":[
        "\u0414\u0435\u043c\u0431\u0430"
    ],
    "name:urd_x_preferred":[
        "\u0688\u06cc\u0645\u0628\u0627"
    ],
    "name:vie_x_preferred":[
        "Demba"
    ],
    "wof:name":"Demba",
    "wof:placetype":"locality"
},
  "geometry": {"coordinates":[-14.68333,11.66667],"type":"Point"}
}