{
  "type": "Feature",
  "properties": {
    "gn:admin1_code":"00",
    "gn:asciiname":"Demba",
    "gn:country_code":"GW",
    "gn:dem":49,
    "gn:feature_class":"P",
    "gn:feature_code":"PPL",
    "gn:name":"Demba",
    "gn:population":0,
    "gn:timezone":"Africa/Bissau",
    "iso:country":"GW",
    "name:ceb_x_preferred":[
        "Demba"
    ],
    "name:deu_x_preferred":[
        "Demba"
    ],
    "name:ron_x_preferred":[
        "Demba"
    ],
    "name:swe_x_preferred":[
        "Demba"
    ],
    "wof:name":"Demba",
    "wof:placetype":"locality"
},
  "geometry": {"coordinates":[-14.68333,11.66667],"type":"Point"}
}