{
  "type": "Feature",
  "properties": {
    "gn:admin1_code":"00",
    "gn:asciiname":"Dando",
    "gn:country_code":"GW",
    "gn:dem":8,
    "gn:feature_class":"P",
    "gn:feature_code":"PPL",
    "gn:name":"Dando",
    "gn:population":0,
    "gn:timezone":"Africa/Bissau",
    "iso:country":"GW",
    "name:fas_x_preferred":[
        "\u062f\u0646\u062f\u0648"
    ],
    "wof:name":"Dando",
    "wof:placetype":"locality"
},
  "geometry": {"coordinates":[-14.88333,11.76667],"type":"Point"}
}