{
  "type": "Feature",
  "properties": {
    "gn:admin1_code":"00",
    "gn:asciiname":"Badem",
    "gn:country_code":"GW",
    "gn:dem":34,
    "gn:feature_class":"P",
    "gn:feature_code":"PPL",
    "gn:name":"Badem",
    "gn:population":0,
    "gn:timezone":"Africa/Bissau",
    "iso:country":"GW",
    "name:ceb_x_preferred":[
        "Badem"
    ],
    "name:deu_x_preferred":[
        "Badem"
    ],
    "name:epo_x_preferred":[
        "Badem"
    ],
    "name:eus_x_preferred":[
        "Badem"
    ],
    "name:fas_x_preferred":[
        "\u0628\u0627\u062f\u0645"
    ],
    "name:fra_x_preferred":[
        "Badem"
    ],
    "name:hun_x_preferred":[
        "Badem"
    ],
    "name:ita_x_preferred":[
        "Badem"
    ],
    "name:kaz_x_preferred":[
        "\u0411\u0430\u0434\u0435\u043c"
    ],
    "name:kir_x_preferred":[
        "\u0411\u0430\u0434\u0435\u043c"
    ],
    "name:ltz_x_preferred":[
        "Badem"
    ],
    "name:msa_x_preferred":[
        "Badem"
    ],
    "name:nld_x_preferred":[
        "Badem"
    ],
    "name:pol_x_preferred":[
        "Badem"
    ],
    "name:por_x_preferred":[
        "Badem"
    ],
    "name:ron_x_preferred":[
        "Badem"
    ],
    "name:rus_x_preferred":[
        "\u0411\u0430\u0434\u0435\u043c"
    ],
    "name:spa_x_preferred":[
        "Badem"
    ],
    "name:srp_x_preferred":[
        "\u0411\u0430\u0434\u0435\u043c"
    ],
    "name:ukr_x_preferred":[
        "\u0411\u0430\u0434\u0435\u043c"
    ],
    "name:uzb_x_preferred":[
        "Badem"
    ],
    "name:vie_x_preferred":[
        "Badem"
    ],
    "name:vol_x_preferred":[
        "Badem"
    ],
    "name:war_x_preferred":[
        "Badem"
    ],
    "name:zho_x_preferred":[
        "\u5df4\u5fb7\u59c6"
    ],
    "wof:name":"Badem",
    "wof:placetype":"locality"
},
  "geometry": {"coordinates":[-15.11667,12.61667],"type":"Point"}
}