{
  "type": "Feature",
  "properties": {
    "gn:admin1_code":"00",
    "gn:asciiname":"Bairro Joli",
    "gn:country_code":"GW",
    "gn:dem":34,
    "gn:feature_class":"P",
    "gn:feature_code":"PPL",
    "gn:name":"Bairro Joli",
    "gn:population":0,
    "gn:timezone":"Africa/Bissau",
    "iso:country":"GW",
    "wof:name":"Bairro Joli",
    "wof:placetype":"locality"
},
  "geometry": {"coordinates":[-14.85,12.05],"type":"Point"}
}