{
  "type": "Feature",
  "properties": {
    "gn:admin1_code":"06",
    "gn:asciiname":"Barraca Lugar",
    "gn:country_code":"GW",
    "gn:dem":24,
    "gn:feature_class":"P",
    "gn:feature_code":"PPL",
    "gn:name":"Barraca Lugar",
    "gn:population":0,
    "gn:timezone":"Africa/Bissau",
    "iso:country":"GW",
    "wof:name":"Barraca Lugar",
    "wof:placetype":"locality"
},
  "geometry": {"coordinates":[-16.16832999999999,12.43528],"type":"Point"}
}