{
  "type": "Feature",
  "properties": {
    "gn:admin1_code":"00",
    "gn:asciiname":"Anonho",
    "gn:cc2":"GW",
    "gn:country_code":"GW",
    "gn:dem":-9999,
    "gn:feature_class":"P",
    "gn:feature_code":"PPL",
    "gn:name":"Anonh\u00f4",
    "gn:population":0,
    "gn:timezone":"Africa/Bissau",
    "iso:country":"GW",
    "name:und_x_variant":[
        "Ananh\u00f4",
        "Amonho",
        "An-onhe",
        "Anonh\u00f4"
    ],
    "wof:name":"Anonho",
    "wof:placetype":"locality"
},
  "geometry": {"coordinates":[-16.15,11.23333],"type":"Point"}
}