{
  "type": "Feature",
  "properties": {
    "gn:admin1_code":"00",
    "gn:asciiname":"Sincha Ture",
    "gn:country_code":"GW",
    "gn:dem":58,
    "gn:feature_class":"P",
    "gn:feature_code":"PPL",
    "gn:name":"Sinch\u00e3 Tur\u00e8",
    "gn:population":0,
    "gn:timezone":"Africa/Bissau",
    "iso:country":"GW",
    "wof:name":"Sincha Ture",
    "wof:placetype":"locality"
},
  "geometry": {"coordinates":[-14.65,12.46667],"type":"Point"}
}