{
  "type": "Feature",
  "properties": {
    "gn:admin1_code":"00",
    "gn:asciiname":"Bantaja",
    "gn:cc2":"GW",
    "gn:country_code":"GW",
    "gn:dem":12,
    "gn:feature_class":"P",
    "gn:feature_code":"PPL",
    "gn:name":"Bantaj\u00e3",
    "gn:population":0,
    "gn:timezone":"Africa/Bissau",
    "iso:country":"GW",
    "name:und_x_variant":[
        "Bantanjam",
        "Bantaj\u00e3"
    ],
    "wof:name":"Bantaja",
    "wof:placetype":"locality"
},
  "geometry": {"coordinates":[-15.21667,12.48333],"type":"Point"}
}