{
  "type": "Feature",
  "properties": {
    "gn:admin1_code":"04",
    "gn:asciiname":"Cumbule",
    "gn:cc2":"GW",
    "gn:country_code":"GW",
    "gn:dem":18,
    "gn:feature_class":"P",
    "gn:feature_code":"PPL",
    "gn:name":"Cumbule",
    "gn:population":0,
    "gn:timezone":"Africa/Bissau",
    "iso:country":"GW",
    "name:und_x_variant":[
        "Bi\u00far",
        "Cumbule"
    ],
    "wof:name":"Cumbule",
    "wof:placetype":"locality"
},
  "geometry": {"coordinates":[-15.43417,12.095],"type":"Point"}
}