{
  "type": "Feature",
  "properties": {
    "gn:admin1_code":"00",
    "gn:asciiname":"Somba",
    "gn:country_code":"GW",
    "gn:dem":26,
    "gn:feature_class":"P",
    "gn:feature_code":"PPL",
    "gn:name":"Somba",
    "gn:population":0,
    "gn:timezone":"Africa/Bissau",
    "iso:country":"GW",
    "name:ceb_x_preferred":[
        "Somba"
    ],
    "name:fra_x_preferred":[
        "Somba"
    ],
    "name:swe_x_preferred":[
        "Somba"
    ],
    "wof:name":"Somba",
    "wof:placetype":"locality"
},
  "geometry": {"coordinates":[-15.36667,11.43333],"type":"Point"}
}