{
  "type": "Feature",
  "properties": {
    "gn:admin1_code":"04",
    "gn:asciiname":"Mandingara",
    "gn:country_code":"GW",
    "gn:dem":22,
    "gn:feature_class":"P",
    "gn:feature_code":"PPL",
    "gn:name":"Mandingar\u00e1",
    "gn:population":0,
    "gn:timezone":"Africa/Bissau",
    "iso:country":"GW",
    "wof:name":"Mandingara",
    "wof:placetype":"locality"
},
  "geometry": {"coordinates":[-15.19361,12.17083],"type":"Point"}
}