{
  "type": "Feature",
  "properties": {
    "gn:admin1_code":"00",
    "gn:asciiname":"Sare Saco",
    "gn:cc2":"GW",
    "gn:country_code":"GW",
    "gn:dem":42,
    "gn:feature_class":"P",
    "gn:feature_code":"PPL",
    "gn:name":"Sare Saco",
    "gn:population":0,
    "gn:timezone":"Africa/Bissau",
    "iso:country":"GW",
    "name:und_x_variant":[
        "Sare Sag\u00f3",
        "Sare Saco"
    ],
    "wof:name":"Sare Saco",
    "wof:placetype":"locality"
},
  "geometry": {"coordinates":[-14.86667,12.48333],"type":"Point"}
}