{
  "type": "Feature",
  "properties": {
    "gn:admin1_code":"00",
    "gn:asciiname":"Sincha Demba Ialare",
    "gn:cc2":"GW",
    "gn:country_code":"GW",
    "gn:dem":62,
    "gn:feature_class":"P",
    "gn:feature_code":"PPL",
    "gn:name":"Sinch\u00e3 Demba Ialare",
    "gn:population":0,
    "gn:timezone":"Africa/Bissau",
    "iso:country":"GW",
    "name:und_x_variant":[
        "Darsalame",
        "Sinch\u00e3 Demba Ialare"
    ],
    "wof:name":"Sincha Demba Ialare",
    "wof:placetype":"locality"
},
  "geometry": {"coordinates":[-14.38333,12.25],"type":"Point"}
}