{
  "type": "Feature",
  "properties": {
    "gn:admin1_code":"00",
    "gn:asciiname":"Sincha Cucha",
    "gn:country_code":"GW",
    "gn:dem":59,
    "gn:feature_class":"P",
    "gn:feature_code":"PPL",
    "gn:name":"Sinch\u00e3 Cuch\u00e1",
    "gn:population":0,
    "gn:timezone":"Africa/Bissau",
    "iso:country":"GW",
    "wof:name":"Sincha Cucha",
    "wof:placetype":"locality"
},
  "geometry": {"coordinates":[-14.63333,11.66667],"type":"Point"}
}