{
  "type": "Feature",
  "properties": {
    "gn:admin1_code":"00",
    "gn:asciiname":"Serracao Morais",
    "gn:country_code":"GW",
    "gn:dem":17,
    "gn:feature_class":"P",
    "gn:feature_code":"PPL",
    "gn:name":"Serra\u00e7\u00e3o Morais",
    "gn:population":0,
    "gn:timezone":"Africa/Bissau",
    "iso:country":"GW",
    "wof:name":"Serracao Morais",
    "wof:placetype":"locality"
},
  "geometry": {"coordinates":[-15.41667,12.43333],"type":"Point"}
}