{
  "type": "Feature",
  "properties": {
    "gn:admin1_code":"00",
    "gn:asciiname":"Gubia Mancanha",
    "gn:country_code":"GW",
    "gn:dem":23,
    "gn:feature_class":"P",
    "gn:feature_code":"PPL",
    "gn:name":"Gubia Mancanha",
    "gn:population":0,
    "gn:timezone":"Africa/Bissau",
    "iso:country":"GW",
    "wof:name":"Gubia Mancanha",
    "wof:placetype":"locality"
},
  "geometry": {"coordinates":[-15.35,11.51667],"type":"Point"}
}