{
  "type": "Feature",
  "properties": {
    "gn:admin1_code":"00",
    "gn:asciiname":"Gundague Futa-Fula",
    "gn:country_code":"GW",
    "gn:dem":29,
    "gn:feature_class":"P",
    "gn:feature_code":"PPL",
    "gn:name":"Gundagu\u00ea Futa-Fula",
    "gn:population":0,
    "gn:timezone":"Africa/Bissau",
    "iso:country":"GW",
    "wof:name":"Gundague Futa-Fula",
    "wof:placetype":"locality"
},
  "geometry": {"coordinates":[-14.91667,11.91667],"type":"Point"}
}