{
  "type": "Feature",
  "properties": {
    "gn:admin1_code":"04",
    "gn:asciiname":"Galo Gega",
    "gn:cc2":"GW",
    "gn:country_code":"GW",
    "gn:dem":36,
    "gn:feature_class":"P",
    "gn:feature_code":"PPL",
    "gn:name":"Galo Gega",
    "gn:population":0,
    "gn:timezone":"Africa/Bissau",
    "iso:country":"GW",
    "name:und_x_variant":[
        "Galo Jega",
        "Galo Gega"
    ],
    "wof:name":"Galo Gega",
    "wof:placetype":"locality"
},
  "geometry": {"coordinates":[-15.06833,12.65583],"type":"Point"}
}