{
  "type": "Feature",
  "properties": {
    "gn:admin1_code":"00",
    "gn:asciiname":"Canhaque",
    "gn:country_code":"GW",
    "gn:dem":17,
    "gn:feature_class":"P",
    "gn:feature_code":"PPL",
    "gn:name":"Canhaque",
    "gn:population":0,
    "gn:timezone":"Africa/Bissau",
    "iso:country":"GW",
    "wof:name":"Canhaque",
    "wof:placetype":"locality"
},
  "geometry": {"coordinates":[-16.06667,11.78333],"type":"Point"}
}