{
  "type": "Feature",
  "properties": {
    "gn:admin1_code":"00",
    "gn:asciiname":"Sucuta",
    "gn:cc2":"GW",
    "gn:country_code":"GW",
    "gn:dem":14,
    "gn:feature_class":"P",
    "gn:feature_code":"PPL",
    "gn:name":"Sucuta",
    "gn:population":0,
    "gn:timezone":"Africa/Bissau",
    "iso:country":"GW",
    "name:und_x_variant":[
        "Cauntol",
        "Caunto",
        "Sucuta"
    ],
    "wof:name":"Sucuta",
    "wof:placetype":"locality"
},
  "geometry": {"coordinates":[-15.35,11.46667],"type":"Point"}
}