{
  "type": "Feature",
  "properties": {
    "gn:admin1_code":"06",
    "gn:asciiname":"Jete",
    "gn:country_code":"GW",
    "gn:dem":20,
    "gn:feature_class":"P",
    "gn:feature_code":"PPL",
    "gn:name":"Jete",
    "gn:population":0,
    "gn:timezone":"Africa/Bissau",
    "iso:country":"GW",
    "wof:name":"Jete",
    "wof:placetype":"locality"
},
  "geometry": {"coordinates":[-15.89611,12.00667],"type":"Point"}
}