{
  "type": "Feature",
  "properties": {
    "gn:admin1_code":"00",
    "gn:asciiname":"Dembel Uri",
    "gn:cc2":"GW",
    "gn:country_code":"GW",
    "gn:dem":50,
    "gn:feature_class":"P",
    "gn:feature_code":"PPL",
    "gn:name":"Dembel Uri",
    "gn:population":0,
    "gn:timezone":"Africa/Bissau",
    "iso:country":"GW",
    "name:und_x_variant":[
        "Dambel Uri",
        "Dembel Uri"
    ],
    "wof:name":"Dembel Uri",
    "wof:placetype":"locality"
},
  "geometry": {"coordinates":[-14.41667,12.28333],"type":"Point"}
}