{
  "type": "Feature",
  "properties": {
    "gn:admin1_code":"00",
    "gn:asciiname":"Gunco",
    "gn:country_code":"GW",
    "gn:dem":25,
    "gn:feature_class":"P",
    "gn:feature_code":"PPL",
    "gn:name":"Gunc\u00f3",
    "gn:population":0,
    "gn:timezone":"Africa/Bissau",
    "iso:country":"GW",
    "wof:name":"Gunco",
    "wof:placetype":"locality"
},
  "geometry": {"coordinates":[-16.05,12.18333],"type":"Point"}
}