{
  "type": "Feature",
  "properties": {
    "gn:admin1_code":"06",
    "gn:asciiname":"Ganture",
    "gn:country_code":"GW",
    "gn:dem":12,
    "gn:feature_class":"P",
    "gn:feature_code":"PPL",
    "gn:name":"Gantur\u00e8",
    "gn:population":0,
    "gn:timezone":"Africa/Bissau",
    "iso:country":"GW",
    "wof:name":"Ganture",
    "wof:placetype":"locality"
},
  "geometry": {"coordinates":[-15.52861,12.41417],"type":"Point"}
}