{
  "type": "Feature",
  "properties": {
    "gn:admin1_code":"00",
    "gn:asciiname":"Pajanhe",
    "gn:country_code":"GW",
    "gn:dem":48,
    "gn:feature_class":"P",
    "gn:feature_code":"PPL",
    "gn:name":"Pajanhe",
    "gn:population":0,
    "gn:timezone":"Africa/Bissau",
    "iso:country":"GW",
    "wof:name":"Pajanhe",
    "wof:placetype":"locality"
},
  "geometry": {"coordinates":[-14.58333,12.18333],"type":"Point"}
}