{
  "type": "Feature",
  "properties": {
    "gn:admin1_code":"00",
    "gn:asciiname":"Cacutunte",
    "gn:country_code":"GW",
    "gn:dem":7,
    "gn:feature_class":"P",
    "gn:feature_code":"PPL",
    "gn:name":"Cacutunte",
    "gn:population":0,
    "gn:timezone":"Africa/Bissau",
    "iso:country":"GW",
    "wof:name":"Cacutunte",
    "wof:placetype":"locality"
},
  "geometry": {"coordinates":[-15.08333,10.98333],"type":"Point"}
}