{
  "type": "Feature",
  "properties": {
    "gn:admin1_code":"04",
    "gn:asciiname":"Jumbembem",
    "gn:country_code":"GW",
    "gn:dem":10,
    "gn:feature_class":"P",
    "gn:feature_code":"PPL",
    "gn:name":"Jumbembem",
    "gn:population":0,
    "gn:timezone":"Africa/Bissau",
    "iso:country":"GW",
    "wof:name":"Jumbembem",
    "wof:placetype":"locality"
},
  "geometry": {"coordinates":[-15.09389,12.57361],"type":"Point"}
}