{
  "type": "Feature",
  "properties": {
    "gn:admin1_code":"00",
    "gn:asciiname":"Mansambo",
    "gn:country_code":"GW",
    "gn:dem":41,
    "gn:feature_class":"P",
    "gn:feature_code":"PPL",
    "gn:name":"Mansambo",
    "gn:population":0,
    "gn:timezone":"Africa/Bissau",
    "iso:country":"GW",
    "wof:name":"Mansambo",
    "wof:placetype":"locality"
},
  "geometry": {"coordinates":[-14.83333,11.88333],"type":"Point"}
}