{
  "type": "Feature",
  "properties": {
    "gn:admin1_code":"00",
    "gn:asciiname":"Naima",
    "gn:country_code":"GW",
    "gn:dem":39,
    "gn:feature_class":"P",
    "gn:feature_code":"PPL",
    "gn:name":"Naima",
    "gn:population":0,
    "gn:timezone":"Africa/Bissau",
    "iso:country":"GW",
    "name:deu_x_preferred":[
        "Naima"
    ],
    "name:fra_x_preferred":[
        "Naima"
    ],
    "name:ita_x_preferred":[
        "Naima"
    ],
    "wof:name":"Naima",
    "wof:placetype":"locality"
},
  "geometry": {"coordinates":[-14.51667,12.41667],"type":"Point"}
}