{
  "type": "Feature",
  "properties": {
    "gn:admin1_code":"00",
    "gn:asciiname":"Gancherno",
    "gn:country_code":"GW",
    "gn:dem":32,
    "gn:feature_class":"P",
    "gn:feature_code":"PPL",
    "gn:name":"Gancherno",
    "gn:population":0,
    "gn:timezone":"Africa/Bissau",
    "iso:country":"GW",
    "wof:name":"Gancherno",
    "wof:placetype":"locality"
},
  "geometry": {"coordinates":[-15.15,11.73333],"type":"Point"}
}