{
  "type": "Feature",
  "properties": {
    "gn:admin1_code":"00",
    "gn:asciiname":"Tassilima",
    "gn:country_code":"GW",
    "gn:dem":67,
    "gn:feature_class":"P",
    "gn:feature_code":"PPL",
    "gn:name":"Tassilim\u00e3",
    "gn:population":0,
    "gn:timezone":"Africa/Bissau",
    "iso:country":"GW",
    "wof:name":"Tassilima",
    "wof:placetype":"locality"
},
  "geometry": {"coordinates":[-14.15,12.26667],"type":"Point"}
}