{
  "type": "Feature",
  "properties": {
    "gn:admin1_code":"00",
    "gn:asciiname":"Samba Ioba",
    "gn:country_code":"GW",
    "gn:dem":58,
    "gn:feature_class":"P",
    "gn:feature_code":"PPL",
    "gn:name":"Samba Iob\u00e0",
    "gn:population":0,
    "gn:timezone":"Africa/Bissau",
    "iso:country":"GW",
    "wof:name":"Samba Ioba",
    "wof:placetype":"locality"
},
  "geometry": {"coordinates":[-14.61667,11.66667],"type":"Point"}
}