{
  "type": "Feature",
  "properties": {
    "gn:admin1_code":"00",
    "gn:asciiname":"Ga Formoso",
    "gn:country_code":"GW",
    "gn:dem":14,
    "gn:feature_class":"P",
    "gn:feature_code":"PPL",
    "gn:name":"G\u00e3 Formoso",
    "gn:population":0,
    "gn:timezone":"Africa/Bissau",
    "iso:country":"GW",
    "wof:name":"Ga Formoso",
    "wof:placetype":"locality"
},
  "geometry": {"coordinates":[-15.23333,11.85],"type":"Point"}
}