{
  "type": "Feature",
  "properties": {
    "gn:admin1_code":"00",
    "gn:asciiname":"Sincha Demba",
    "gn:cc2":"GW",
    "gn:country_code":"GW",
    "gn:dem":59,
    "gn:feature_class":"P",
    "gn:feature_code":"PPL",
    "gn:name":"Sinch\u00e3 Demba",
    "gn:population":0,
    "gn:timezone":"Africa/Bissau",
    "iso:country":"GW",
    "name:und_x_variant":[
        "Cumbare",
        "Sinch\u00e3 Demba"
    ],
    "wof:name":"Sincha Demba",
    "wof:placetype":"locality"
},
  "geometry": {"coordinates":[-14.41667,12.23333],"type":"Point"}
}