{
  "type": "Feature",
  "properties": {
    "gn:admin1_code":"00",
    "gn:asciiname":"Tienecunda",
    "gn:cc2":"GW",
    "gn:country_code":"GW",
    "gn:dem":49,
    "gn:feature_class":"P",
    "gn:feature_code":"PPL",
    "gn:name":"Tienecunda",
    "gn:population":0,
    "gn:timezone":"Africa/Bissau",
    "iso:country":"GW",
    "name:und_x_variant":[
        "Tianacunda",
        "Tienecunda"
    ],
    "wof:name":"Tienecunda",
    "wof:placetype":"locality"
},
  "geometry": {"coordinates":[-14.55,12.33333],"type":"Point"}
}