{
  "type": "Feature",
  "properties": {
    "gn:admin1_code":"00",
    "gn:asciiname":"Cabaceira",
    "gn:cc2":"GW",
    "gn:country_code":"GW",
    "gn:dem":8,
    "gn:feature_class":"P",
    "gn:feature_code":"PPL",
    "gn:name":"Cabaceira",
    "gn:population":0,
    "gn:timezone":"Africa/Bissau",
    "iso:country":"GW",
    "name:und_x_variant":[
        "Gantene",
        "Cabaceira"
    ],
    "wof:name":"Cabaceira",
    "wof:placetype":"locality"
},
  "geometry": {"coordinates":[-15.36667,11.51667],"type":"Point"}
}