{
  "type": "Feature",
  "properties": {
    "gn:admin1_code":"00",
    "gn:asciiname":"Sinchuro Paraual",
    "gn:cc2":"GW",
    "gn:country_code":"GW",
    "gn:dem":74,
    "gn:feature_class":"P",
    "gn:feature_code":"PPL",
    "gn:name":"Sinchuro Paraual",
    "gn:population":0,
    "gn:timezone":"Africa/Bissau",
    "iso:country":"GW",
    "name:und_x_variant":[
        "Sinchur Paranale",
        "Sinchuro Paraual"
    ],
    "wof:name":"Sinchuro Paraual",
    "wof:placetype":"locality"
},
  "geometry": {"coordinates":[-14.03333,11.71667],"type":"Point"}
}