{
  "type": "Feature",
  "properties": {
    "gn:admin1_code":"00",
    "gn:asciiname":"Gancula",
    "gn:country_code":"GW",
    "gn:dem":1,
    "gn:feature_class":"P",
    "gn:feature_code":"PPL",
    "gn:name":"Gancula",
    "gn:population":0,
    "gn:timezone":"Africa/Bissau",
    "iso:country":"GW",
    "wof:name":"Gancula",
    "wof:placetype":"locality"
},
  "geometry": {"coordinates":[-15.31667,11.55],"type":"Point"}
}