{
  "type": "Feature",
  "properties": {
    "gn:admin1_code":"00",
    "gn:asciiname":"Fafaco",
    "gn:country_code":"GW",
    "gn:dem":84,
    "gn:feature_class":"P",
    "gn:feature_code":"PPL",
    "gn:name":"Fafac\u00f3",
    "gn:population":0,
    "gn:timezone":"Africa/Bissau",
    "iso:country":"GW",
    "wof:name":"Fafaco",
    "wof:placetype":"locality"
},
  "geometry": {"coordinates":[-14.06667,12.35],"type":"Point"}
}