{
  "type": "Feature",
  "properties": {
    "gn:admin1_code":"00",
    "gn:asciiname":"Amedalai",
    "gn:country_code":"GW",
    "gn:dem":17,
    "gn:feature_class":"P",
    "gn:feature_code":"PPL",
    "gn:name":"Amedalai",
    "gn:population":0,
    "gn:timezone":"Africa/Bissau",
    "iso:country":"GW",
    "wof:name":"Amedalai",
    "wof:placetype":"locality"
},
  "geometry": {"coordinates":[-14.91667,11.98333],"type":"Point"}
}