{
  "type": "Feature",
  "properties": {
    "gn:admin1_code":"00",
    "gn:asciiname":"Geba",
    "gn:country_code":"GW",
    "gn:dem":29,
    "gn:feature_class":"P",
    "gn:feature_code":"PPL",
    "gn:name":"G\u00eaba",
    "gn:population":0,
    "gn:timezone":"Africa/Bissau",
    "iso:country":"GW",
    "name:cat_x_preferred":[
        "Geba"
    ],
    "name:deu_x_preferred":[
        "Geba"
    ],
    "name:pol_x_preferred":[
        "Geba"
    ],
    "wof:name":"Geba",
    "wof:placetype":"locality"
},
  "geometry": {"coordinates":[-14.76667,12.16667],"type":"Point"}
}