{
  "type": "Feature",
  "properties": {
    "gn:admin1_code":"00",
    "gn:asciiname":"Sejo Fula",
    "gn:country_code":"GW",
    "gn:dem":46,
    "gn:feature_class":"P",
    "gn:feature_code":"PPL",
    "gn:name":"Sejo Fula",
    "gn:population":0,
    "gn:timezone":"Africa/Bissau",
    "iso:country":"GW",
    "wof:name":"Sejo Fula",
    "wof:placetype":"locality"
},
  "geometry": {"coordinates":[-14.25,12.51667],"type":"Point"}
}