{
  "type": "Feature",
  "properties": {
    "gn:admin1_code":"06",
    "gn:asciiname":"Apilho Balanta",
    "gn:country_code":"GW",
    "gn:dem":19,
    "gn:feature_class":"P",
    "gn:feature_code":"PPL",
    "gn:name":"Apilho Balanta",
    "gn:population":0,
    "gn:timezone":"Africa/Bissau",
    "iso:country":"GW",
    "wof:name":"Apilho Balanta",
    "wof:placetype":"locality"
},
  "geometry": {"coordinates":[-15.93472,12.34611],"type":"Point"}
}