{
  "type": "Feature",
  "properties": {
    "gn:admin1_code":"00",
    "gn:asciiname":"Brincasse",
    "gn:country_code":"GW",
    "gn:dem":61,
    "gn:feature_class":"P",
    "gn:feature_code":"PPL",
    "gn:name":"Brincasse",
    "gn:population":0,
    "gn:timezone":"Africa/Bissau",
    "iso:country":"GW",
    "wof:name":"Brincasse",
    "wof:placetype":"locality"
},
  "geometry": {"coordinates":[-14.55,12.21667],"type":"Point"}
}