{
  "type": "Feature",
  "properties": {
    "gn:admin1_code":"06",
    "gn:asciiname":"Pece",
    "gn:country_code":"GW",
    "gn:dem":14,
    "gn:feature_class":"P",
    "gn:feature_code":"PPL",
    "gn:name":"Pec\u00e9",
    "gn:population":0,
    "gn:timezone":"Africa/Bissau",
    "iso:country":"GW",
    "wof:name":"Pece",
    "wof:placetype":"locality"
},
  "geometry": {"coordinates":[-15.80667,12.20111],"type":"Point"}
}