{
  "type": "Feature",
  "properties": {
    "gn:admin1_code":"00",
    "gn:asciiname":"Oco Grande",
    "gn:country_code":"GW",
    "gn:dem":4,
    "gn:feature_class":"P",
    "gn:feature_code":"PPL",
    "gn:name":"Oco Grande",
    "gn:population":0,
    "gn:timezone":"Africa/Bissau",
    "iso:country":"GW",
    "wof:name":"Oco Grande",
    "wof:placetype":"locality"
},
  "geometry": {"coordinates":[-15.51667,11.93333],"type":"Point"}
}