{
  "type": "Feature",
  "properties": {
    "gn:admin1_code":"00",
    "gn:asciiname":"Canhanicunda",
    "gn:country_code":"GW",
    "gn:dem":77,
    "gn:feature_class":"P",
    "gn:feature_code":"PPL",
    "gn:name":"Canhanicunda",
    "gn:population":0,
    "gn:timezone":"Africa/Bissau",
    "iso:country":"GW",
    "wof:name":"Canhanicunda",
    "wof:placetype":"locality"
},
  "geometry": {"coordinates":[-13.95,12.33333],"type":"Point"}
}