{
  "type": "Feature",
  "properties": {
    "gn:admin1_code":"00",
    "gn:asciiname":"Jomelcunda",
    "gn:cc2":"GW",
    "gn:country_code":"GW",
    "gn:dem":67,
    "gn:feature_class":"P",
    "gn:feature_code":"PPL",
    "gn:name":"Jomelcunda",
    "gn:population":0,
    "gn:timezone":"Africa/Bissau",
    "iso:country":"GW",
    "name:und_x_variant":[
        "Jamelcunda",
        "Jomelcunda"
    ],
    "wof:name":"Jomelcunda",
    "wof:placetype":"locality"
},
  "geometry": {"coordinates":[-14.08333,12.51667],"type":"Point"}
}