{
  "type": "Feature",
  "properties": {
    "gn:admin1_code":"00",
    "gn:asciiname":"Ida",
    "gn:country_code":"GW",
    "gn:dem":29,
    "gn:feature_class":"P",
    "gn:feature_code":"PPL",
    "gn:name":"Ida",
    "gn:population":0,
    "gn:timezone":"Africa/Bissau",
    "iso:country":"GW",
    "wof:name":"Ida",
    "wof:placetype":"locality"
},
  "geometry": {"coordinates":[-14.88333,11.18333],"type":"Point"}
}