{
  "type": "Feature",
  "properties": {
    "gn:admin1_code":"00",
    "gn:asciiname":"Moia Fara",
    "gn:country_code":"GW",
    "gn:dem":23,
    "gn:feature_class":"P",
    "gn:feature_code":"PPL",
    "gn:name":"Moia Far\u00e1",
    "gn:population":0,
    "gn:timezone":"Africa/Bissau",
    "iso:country":"GW",
    "wof:name":"Moia Fara",
    "wof:placetype":"locality"
},
  "geometry": {"coordinates":[-15.36667,12.23333],"type":"Point"}
}