{
  "type": "Feature",
  "properties": {
    "gn:admin1_code":"00",
    "gn:asciiname":"Chombe",
    "gn:cc2":"GW",
    "gn:country_code":"GW",
    "gn:dem":8,
    "gn:feature_class":"P",
    "gn:feature_code":"PPL",
    "gn:name":"Chomb\u00e8",
    "gn:population":0,
    "gn:timezone":"Africa/Bissau",
    "iso:country":"GW",
    "name:und_x_variant":[
        "Chambam",
        "Chomb\u00e8"
    ],
    "wof:name":"Chombe",
    "wof:placetype":"locality"
},
  "geometry": {"coordinates":[-15.15,11.95],"type":"Point"}
}