{
  "type": "Feature",
  "properties": {
    "gn:admin1_code":"00",
    "gn:asciiname":"Uaqueri",
    "gn:country_code":"GW",
    "gn:dem":6,
    "gn:feature_class":"P",
    "gn:feature_code":"PPL",
    "gn:name":"Uaqueri",
    "gn:population":0,
    "gn:timezone":"Africa/Bissau",
    "iso:country":"GW",
    "wof:name":"Uaqueri",
    "wof:placetype":"locality"
},
  "geometry": {"coordinates":[-15.53333,12.26667],"type":"Point"}
}