{
  "type": "Feature",
  "properties": {
    "gn:admin1_code":"00",
    "gn:asciiname":"Beracolom",
    "gn:cc2":"GW",
    "gn:country_code":"GW",
    "gn:dem":54,
    "gn:feature_class":"P",
    "gn:feature_code":"PPL",
    "gn:name":"Beracolom",
    "gn:population":0,
    "gn:timezone":"Africa/Bissau",
    "iso:country":"GW",
    "name:und_x_variant":[
        "Bercolom",
        "Bercolon",
        "Beracolom"
    ],
    "wof:name":"Beracolom",
    "wof:placetype":"locality"
},
  "geometry": {"coordinates":[-14.78333,12.55],"type":"Point"}
}