{
  "type": "Feature",
  "properties": {
    "gn:admin1_code":"00",
    "gn:asciiname":"Cansamba",
    "gn:country_code":"GW",
    "gn:dem":59,
    "gn:feature_class":"P",
    "gn:feature_code":"PPL",
    "gn:name":"Cansamba",
    "gn:population":0,
    "gn:timezone":"Africa/Bissau",
    "iso:country":"GW",
    "wof:name":"Cansamba",
    "wof:placetype":"locality"
},
  "geometry": {"coordinates":[-14.35,12.28333],"type":"Point"}
}