{
  "type": "Feature",
  "properties": {
    "gn:admin1_code":"00",
    "gn:asciiname":"Ponta Joaquim Mendes",
    "gn:country_code":"GW",
    "gn:dem":27,
    "gn:feature_class":"P",
    "gn:feature_code":"PPL",
    "gn:name":"Ponta Joaquim Mendes",
    "gn:population":0,
    "gn:timezone":"Africa/Bissau",
    "iso:country":"GW",
    "wof:name":"Ponta Joaquim Mendes",
    "wof:placetype":"locality"
},
  "geometry": {"coordinates":[-15.75,12.05],"type":"Point"}
}