{
  "type": "Feature",
  "properties": {
    "gn:admin1_code":"00",
    "gn:asciiname":"Campate",
    "gn:country_code":"GW",
    "gn:dem":54,
    "gn:feature_class":"P",
    "gn:feature_code":"PPL",
    "gn:name":"Campate",
    "gn:population":0,
    "gn:timezone":"Africa/Bissau",
    "iso:country":"GW",
    "wof:name":"Campate",
    "wof:placetype":"locality"
},
  "geometry": {"coordinates":[-14.46667,12.38333],"type":"Point"}
}