{
  "type": "Feature",
  "properties": {
    "gn:admin1_code":"00",
    "gn:asciiname":"Samba Cande",
    "gn:country_code":"GW",
    "gn:dem":60,
    "gn:feature_class":"P",
    "gn:feature_code":"PPL",
    "gn:name":"Samba Cand\u00e8",
    "gn:population":0,
    "gn:timezone":"Africa/Bissau",
    "iso:country":"GW",
    "wof:name":"Samba Cande",
    "wof:placetype":"locality"
},
  "geometry": {"coordinates":[-14.21667,12.53333],"type":"Point"}
}