{
  "type": "Feature",
  "properties": {
    "gn:admin1_code":"00",
    "gn:asciiname":"Brandao",
    "gn:country_code":"GW",
    "gn:dem":30,
    "gn:feature_class":"P",
    "gn:feature_code":"PPL",
    "gn:name":"Brand\u00e3o",
    "gn:population":0,
    "gn:timezone":"Africa/Bissau",
    "iso:country":"GW",
    "wof:name":"Brandao",
    "wof:placetype":"locality"
},
  "geometry": {"coordinates":[-15.31667,11.73333],"type":"Point"}
}