{
  "type": "Feature",
  "properties": {
    "gn:admin1_code":"04",
    "gn:asciiname":"Cubonge",
    "gn:cc2":"GW",
    "gn:country_code":"GW",
    "gn:dem":29,
    "gn:feature_class":"P",
    "gn:feature_code":"PPL",
    "gn:name":"Cubonge",
    "gn:population":0,
    "gn:timezone":"Africa/Bissau",
    "iso:country":"GW",
    "name:und_x_variant":[
        "Cubonje",
        "Cubonge"
    ],
    "wof:name":"Cubonge",
    "wof:placetype":"locality"
},
  "geometry": {"coordinates":[-15.35028,12.13417],"type":"Point"}
}