{
  "type": "Feature",
  "properties": {
    "gn:admin1_code":"04",
    "gn:asciiname":"Gambia",
    "gn:country_code":"GW",
    "gn:dem":9,
    "gn:feature_class":"P",
    "gn:feature_code":"PPL",
    "gn:name":"Gambia",
    "gn:population":0,
    "gn:timezone":"Africa/Bissau",
    "iso:country":"GW",
    "wof:name":"Gambia",
    "wof:placetype":"locality"
},
  "geometry": {"coordinates":[-15.41667,12.05611],"type":"Point"}
}