{
  "type": "Feature",
  "properties": {
    "gn:admin1_code":"00",
    "gn:asciiname":"Sincha Umaro",
    "gn:country_code":"GW",
    "gn:dem":56,
    "gn:feature_class":"P",
    "gn:feature_code":"PPL",
    "gn:name":"Sinch\u00e3 Umaro",
    "gn:population":0,
    "gn:timezone":"Africa/Bissau",
    "iso:country":"GW",
    "wof:name":"Sincha Umaro",
    "wof:placetype":"locality"
},
  "geometry": {"coordinates":[-14.63333,12.03333],"type":"Point"}
}