{
  "type": "Feature",
  "properties": {
    "gn:admin1_code":"06",
    "gn:asciiname":"Amone",
    "gn:country_code":"GW",
    "gn:dem":11,
    "gn:feature_class":"P",
    "gn:feature_code":"PPL",
    "gn:name":"Amone",
    "gn:population":0,
    "gn:timezone":"Africa/Bissau",
    "iso:country":"GW",
    "wof:name":"Amone",
    "wof:placetype":"locality"
},
  "geometry": {"coordinates":[-15.94778,12.35583],"type":"Point"}
}