{
  "type": "Feature",
  "properties": {
    "gn:admin1_code":"00",
    "gn:asciiname":"Dirma",
    "gn:country_code":"GW",
    "gn:dem":60,
    "gn:feature_class":"P",
    "gn:feature_code":"PPL",
    "gn:name":"Dirma",
    "gn:population":0,
    "gn:timezone":"Africa/Bissau",
    "iso:country":"GW",
    "name:fin_x_preferred":[
        "Dirma"
    ],
    "name:fra_x_preferred":[
        "Dirma"
    ],
    "name:ita_x_preferred":[
        "Dirma"
    ],
    "name:nld_x_preferred":[
        "Dirma"
    ],
    "name:spa_x_preferred":[
        "Dirma"
    ],
    "name:zho_x_preferred":[
        "\u8fea\u723e\u99ac"
    ],
    "wof:name":"Dirma",
    "wof:placetype":"locality"
},
  "geometry": {"coordinates":[-14.65,11.58333],"type":"Point"}
}