{
  "type": "Feature",
  "properties": {
    "gn:admin1_code":"00",
    "gn:asciiname":"Ponta Gomes",
    "gn:cc2":"GW",
    "gn:country_code":"GW",
    "gn:dem":4,
    "gn:feature_class":"P",
    "gn:feature_code":"PPL",
    "gn:name":"Ponta Gomes",
    "gn:population":0,
    "gn:timezone":"Africa/Bissau",
    "iso:country":"GW",
    "name:und_x_variant":[
        "Ponta Lera",
        "Ponta Gomes"
    ],
    "wof:name":"Ponta Gomes",
    "wof:placetype":"locality"
},
  "geometry": {"coordinates":[-15.58333,11.93333],"type":"Point"}
}