{
  "type": "Feature",
  "properties": {
    "gn:admin1_code":"06",
    "gn:asciiname":"Berame",
    "gn:country_code":"GW",
    "gn:dem":20,
    "gn:feature_class":"P",
    "gn:feature_code":"PPL",
    "gn:name":"Berame",
    "gn:population":0,
    "gn:timezone":"Africa/Bissau",
    "iso:country":"GW",
    "wof:name":"Berame",
    "wof:placetype":"locality"
},
  "geometry": {"coordinates":[-16.21472,12.11111],"type":"Point"}
}