{
  "type": "Feature",
  "properties": {
    "gn:admin1_code":"06",
    "gn:asciiname":"Barraca Begoa",
    "gn:country_code":"GW",
    "gn:dem":28,
    "gn:feature_class":"P",
    "gn:feature_code":"PPL",
    "gn:name":"Barraca Bego\u00e1",
    "gn:population":0,
    "gn:timezone":"Africa/Bissau",
    "iso:country":"GW",
    "wof:name":"Barraca Begoa",
    "wof:placetype":"locality"
},
  "geometry": {"coordinates":[-16.13222,12.44833],"type":"Point"}
}