{
  "type": "Feature",
  "properties": {
    "gn:admin1_code":"00",
    "gn:asciiname":"Afia",
    "gn:country_code":"GW",
    "gn:dem":74,
    "gn:feature_class":"P",
    "gn:feature_code":"PPL",
    "gn:name":"\u00c1fi\u00e0",
    "gn:population":0,
    "gn:timezone":"Africa/Bissau",
    "iso:country":"GW",
    "wof:name":"Afia",
    "wof:placetype":"locality"
},
  "geometry": {"coordinates":[-13.95,12.35],"type":"Point"}
}