{
  "type": "Feature",
  "properties": {
    "gn:admin1_code":"00",
    "gn:asciiname":"Sincha Demba Jamanca",
    "gn:country_code":"GW",
    "gn:dem":48,
    "gn:feature_class":"P",
    "gn:feature_code":"PPL",
    "gn:name":"Sinch\u00e3 Demba Jamanca",
    "gn:population":0,
    "gn:timezone":"Africa/Bissau",
    "iso:country":"GW",
    "wof:name":"Sincha Demba Jamanca",
    "wof:placetype":"locality"
},
  "geometry": {"coordinates":[-14.21667,12.26667],"type":"Point"}
}