{
  "type": "Feature",
  "properties": {
    "gn:admin1_code":"04",
    "gn:asciiname":"Canico Tumana",
    "gn:country_code":"GW",
    "gn:dem":36,
    "gn:feature_class":"P",
    "gn:feature_code":"PPL",
    "gn:name":"Canic\u00f3 Tuman\u00e1",
    "gn:population":0,
    "gn:timezone":"Africa/Bissau",
    "iso:country":"GW",
    "wof:name":"Canico Tumana",
    "wof:placetype":"locality"
},
  "geometry": {"coordinates":[-15.26194,12.52222],"type":"Point"}
}