{
  "type": "Feature",
  "properties": {
    "gn:admin1_code":"00",
    "gn:asciiname":"Cane",
    "gn:country_code":"GW",
    "gn:dem":22,
    "gn:feature_class":"P",
    "gn:feature_code":"PPL",
    "gn:name":"Cane",
    "gn:population":0,
    "gn:timezone":"Africa/Bissau",
    "iso:country":"GW",
    "name:cat_x_preferred":[
        "Cane"
    ],
    "name:ceb_x_preferred":[
        "Cane"
    ],
    "name:deu_x_preferred":[
        "Cane"
    ],
    "name:fra_x_preferred":[
        "Cane"
    ],
    "name:ita_x_preferred":[
        "Cane"
    ],
    "name:jpn_x_preferred":[
        "\u30b1\u30fc\u30f3"
    ],
    "name:nld_x_preferred":[
        "Cane"
    ],
    "name:srp_x_preferred":[
        "Cane"
    ],
    "name:swe_x_preferred":[
        "Cane"
    ],
    "wof:name":"Cane",
    "wof:placetype":"locality"
},
  "geometry": {"coordinates":[-15.58333,11.55],"type":"Point"}
}