{
  "type": "Feature",
  "properties": {
    "gn:admin1_code":"00",
    "gn:asciiname":"Sincha Mansaroto",
    "gn:cc2":"GW",
    "gn:country_code":"GW",
    "gn:dem":36,
    "gn:feature_class":"P",
    "gn:feature_code":"PPL",
    "gn:name":"Sinch\u00e3 Mansaroto",
    "gn:population":0,
    "gn:timezone":"Africa/Bissau",
    "iso:country":"GW",
    "name:und_x_variant":[
        "Sinch\u00e3 Mansarr\u00f4to",
        "Sinch\u00e3 Mansaroto"
    ],
    "wof:name":"Sincha Mansaroto",
    "wof:placetype":"locality"
},
  "geometry": {"coordinates":[-15.13333,12.48333],"type":"Point"}
}