{
  "type": "Feature",
  "properties": {
    "gn:admin1_code":"00",
    "gn:asciiname":"Bruce",
    "gn:cc2":"GW",
    "gn:country_code":"GW",
    "gn:dem":12,
    "gn:feature_class":"P",
    "gn:feature_code":"PPL",
    "gn:name":"Bruce",
    "gn:population":0,
    "gn:timezone":"Africa/Bissau",
    "iso:country":"GW",
    "name:und_x_variant":[
        "Brusso",
        "Bruce"
    ],
    "wof:name":"Bruce",
    "wof:placetype":"locality"
},
  "geometry": {"coordinates":[-16.25,11.25],"type":"Point"}
}