{
  "type": "Feature",
  "properties": {
    "gn:admin1_code":"06",
    "gn:asciiname":"Barraca Bambore",
    "gn:country_code":"GW",
    "gn:dem":31,
    "gn:feature_class":"P",
    "gn:feature_code":"PPL",
    "gn:name":"Barraca Bambor\u00e9",
    "gn:population":0,
    "gn:timezone":"Africa/Bissau",
    "iso:country":"GW",
    "wof:name":"Barraca Bambore",
    "wof:placetype":"locality"
},
  "geometry": {"coordinates":[-16.2025,12.44972],"type":"Point"}
}