{
  "type": "Feature",
  "properties": {
    "gn:admin1_code":"00",
    "gn:asciiname":"Sare Pate",
    "gn:country_code":"GW",
    "gn:dem":42,
    "gn:feature_class":"P",
    "gn:feature_code":"PPL",
    "gn:name":"Sare Pat\u00e8",
    "gn:population":0,
    "gn:timezone":"Africa/Bissau",
    "iso:country":"GW",
    "wof:name":"Sare Pate",
    "wof:placetype":"locality"
},
  "geometry": {"coordinates":[-14.78333,12.48333],"type":"Point"}
}