{
  "type": "Feature",
  "properties": {
    "gn:admin1_code":"00",
    "gn:asciiname":"Intusso",
    "gn:cc2":"GW",
    "gn:country_code":"GW",
    "gn:dem":21,
    "gn:feature_class":"P",
    "gn:feature_code":"PPL",
    "gn:name":"Intusso",
    "gn:population":0,
    "gn:timezone":"Africa/Bissau",
    "iso:country":"GW",
    "name:und_x_variant":[
        "Intussi",
        "Intusso"
    ],
    "wof:name":"Intusso",
    "wof:placetype":"locality"
},
  "geometry": {"coordinates":[-15.26667,11.46667],"type":"Point"}
}