{
  "type": "Feature",
  "properties": {
    "gn:admin1_code":"00",
    "gn:asciiname":"Camande",
    "gn:country_code":"GW",
    "gn:dem":40,
    "gn:feature_class":"P",
    "gn:feature_code":"PPL",
    "gn:name":"Camand\u00e9",
    "gn:population":0,
    "gn:timezone":"Africa/Bissau",
    "iso:country":"GW",
    "wof:name":"Camande",
    "wof:placetype":"locality"
},
  "geometry": {"coordinates":[-14.45,12.36667],"type":"Point"}
}