{
  "type": "Feature",
  "properties": {
    "gn:admin1_code":"04",
    "gn:asciiname":"Mantefa",
    "gn:country_code":"GW",
    "gn:dem":27,
    "gn:feature_class":"P",
    "gn:feature_code":"PPL",
    "gn:name":"Mantefa",
    "gn:population":0,
    "gn:timezone":"Africa/Bissau",
    "iso:country":"GW",
    "wof:name":"Mantefa",
    "wof:placetype":"locality"
},
  "geometry": {"coordinates":[-15.32,12.10556],"type":"Point"}
}