{
  "type": "Feature",
  "properties": {
    "gn:admin1_code":"04",
    "gn:asciiname":"Canfanda",
    "gn:country_code":"GW",
    "gn:dem":28,
    "gn:feature_class":"P",
    "gn:feature_code":"PPL",
    "gn:name":"Canfanda",
    "gn:population":0,
    "gn:timezone":"Africa/Bissau",
    "iso:country":"GW",
    "wof:name":"Canfanda",
    "wof:placetype":"locality"
},
  "geometry": {"coordinates":[-15.28667,12.29972],"type":"Point"}
}