{
  "type": "Feature",
  "properties": {
    "gn:admin1_code":"00",
    "gn:asciiname":"Gundaga Primeiro",
    "gn:country_code":"GW",
    "gn:dem":37,
    "gn:feature_class":"P",
    "gn:feature_code":"PPL",
    "gn:name":"Gundag\u00e0 Primeiro",
    "gn:population":0,
    "gn:timezone":"Africa/Bissau",
    "iso:country":"GW",
    "wof:name":"Gundaga Primeiro",
    "wof:placetype":"locality"
},
  "geometry": {"coordinates":[-14.15,12.65],"type":"Point"}
}