{
  "type": "Feature",
  "properties": {
    "gn:admin1_code":"00",
    "gn:asciiname":"Betaque",
    "gn:cc2":"GW",
    "gn:country_code":"GW",
    "gn:dem":5,
    "gn:feature_class":"P",
    "gn:feature_code":"PPL",
    "gn:name":"Betaque",
    "gn:population":0,
    "gn:timezone":"Africa/Bissau",
    "iso:country":"GW",
    "name:und_x_variant":[
        "Beteque",
        "Betaque"
    ],
    "wof:name":"Betaque",
    "wof:placetype":"locality"
},
  "geometry": {"coordinates":[-15.96667,11.96667],"type":"Point"}
}