{
  "type": "Feature",
  "properties": {
    "gn:admin1_code":"00",
    "gn:asciiname":"Tendinto",
    "gn:country_code":"GW",
    "gn:dem":52,
    "gn:feature_class":"P",
    "gn:feature_code":"PPL",
    "gn:name":"Tendinto",
    "gn:population":0,
    "gn:timezone":"Africa/Bissau",
    "iso:country":"GW",
    "wof:name":"Tendinto",
    "wof:placetype":"locality"
},
  "geometry": {"coordinates":[-14.66667,12.61667],"type":"Point"}
}