{
  "type": "Feature",
  "properties": {
    "gn:admin1_code":"00",
    "gn:asciiname":"Missira Balanta",
    "gn:country_code":"GW",
    "gn:dem":24,
    "gn:feature_class":"P",
    "gn:feature_code":"PPL",
    "gn:name":"Missir\u00e1 Balanta",
    "gn:population":0,
    "gn:timezone":"Africa/Bissau",
    "iso:country":"GW",
    "wof:name":"Missira Balanta",
    "wof:placetype":"locality"
},
  "geometry": {"coordinates":[-15.21667,11.51667],"type":"Point"}
}