{
  "type": "Feature",
  "properties": {
    "gn:admin1_code":"00",
    "gn:asciiname":"Sincha Portari",
    "gn:cc2":"GW",
    "gn:country_code":"GW",
    "gn:dem":49,
    "gn:feature_class":"P",
    "gn:feature_code":"PPL",
    "gn:name":"Sinch\u00e3 Portari",
    "gn:population":0,
    "gn:timezone":"Africa/Bissau",
    "iso:country":"GW",
    "name:und_x_variant":[
        "Sinch\u00e3 Fod\u00e8 Jau",
        "Sinch\u00e3 Portari"
    ],
    "wof:name":"Sincha Portari",
    "wof:placetype":"locality"
},
  "geometry": {"coordinates":[-14.96667,12.66667],"type":"Point"}
}