{
  "type": "Feature",
  "properties": {
    "gn:admin1_code":"00",
    "gn:asciiname":"Code",
    "gn:country_code":"GW",
    "gn:dem":80,
    "gn:feature_class":"P",
    "gn:feature_code":"PPL",
    "gn:name":"C\u00f3d\u00e8",
    "gn:population":0,
    "gn:timezone":"Africa/Bissau",
    "iso:country":"GW",
    "name:afr_x_preferred":[
        "Kode"
    ],
    "name:ara_x_preferred":[
        "\u062a\u0631\u0645\u064a\u0632"
    ],
    "name:bel_x_preferred":[
        "\u041a\u043e\u0434"
    ],
    "name:ben_x_preferred":[
        "\u0995\u09cb\u09a1"
    ],
    "name:bos_x_preferred":[
        "Kod"
    ],
    "name:bul_x_preferred":[
        "\u041a\u043e\u0434"
    ],
    "name:cat_x_preferred":[
        "Codi"
    ],
    "name:ces_x_preferred":[
        "K\u00f3d"
    ],
    "name:ckb_x_preferred":[
        "\u06a9\u06c6\u062f"
    ],
    "name:dan_x_preferred":[
        "Kode"
    ],
    "name:deu_x_preferred":[
        "Code"
    ],
    "name:ell_x_preferred":[
        "\u039a\u03ce\u03b4\u03b9\u03ba\u03b1\u03c2"
    ],
    "name:epo_x_preferred":[
        "Kodo"
    ],
    "name:est_x_preferred":[
        "Kood"
    ],
    "name:eus_x_preferred":[
        "Kode"
    ],
    "name:fin_x_preferred":[
        "Koodi"
    ],
    "name:fra_x_preferred":[
        "Code"
    ],
    "name:gle_x_preferred":[
        "C\u00f3d"
    ],
    "name:heb_x_preferred":[
        "\u05e7\u05d5\u05d3"
    ],
    "name:hrv_x_preferred":[
        "Kod"
    ],
    "name:hun_x_preferred":[
        "K\u00f3d"
    ],
    "name:hye_x_preferred":[
        "\u053f\u0578\u0564"
    ],
    "name:ind_x_preferred":[
        "Kode"
    ],
    "name:ita_x_preferred":[
        "Codice"
    ],
    "name:kaz_x_preferred":[
        "\u041a\u043e\u0434"
    ],
    "name:kor_x_preferred":[
        "\ubd80\ud638"
    ],
    "name:lat_x_preferred":[
        "Codex"
    ],
    "name:nld_x_preferred":[
        "Code"
    ],
    "name:nno_x_preferred":[
        "Kode"
    ],
    "name:nor_x_preferred":[
        "Kode"
    ],
    "name:pol_x_preferred":[
        "Kod"
    ],
    "name:por_x_preferred":[
        "Codifica\u00e7\u00e3o"
    ],
    "name:rus_x_preferred":[
        "\u041a\u043e\u0434"
    ],
    "name:sco_x_preferred":[
        "Code"
    ],
    "name:slk_x_preferred":[
        "K\u00f3d"
    ],
    "name:sqi_x_preferred":[
        "Kodi"
    ],
    "name:srp_x_preferred":[
        "\u041a\u043e\u0434"
    ],
    "name:swe_x_preferred":[
        "Kodning"
    ],
    "name:tel_x_preferred":[
        "\u0c15\u0c4b\u0c21\u0c4d"
    ],
    "name:tgl_x_preferred":[
        "Code"
    ],
    "name:tha_x_preferred":[
        "\u0e23\u0e2b\u0e31\u0e2a"
    ],
    "name:tur_x_preferred":[
        "Kod"
    ],
    "name:ukr_x_preferred":[
        "\u041a\u043e\u0434"
    ],
    "name:urd_x_preferred":[
        "\u0631\u0645\u0632"
    ],
    "name:uzb_x_preferred":[
        "Kod"
    ],
    "name:vie_x_preferred":[
        "M\u00e3 hi\u1ec7u"
    ],
    "wof:name":"Code",
    "wof:placetype":"locality"
},
  "geometry": {"coordinates":[-13.96667,12.43333],"type":"Point"}
}