{
  "type": "Feature",
  "properties": {
    "gn:admin1_code":"00",
    "gn:asciiname":"Bonjendem",
    "gn:cc2":"GW",
    "gn:country_code":"GW",
    "gn:dem":35,
    "gn:feature_class":"P",
    "gn:feature_code":"PPL",
    "gn:name":"Bonjendem",
    "gn:population":0,
    "gn:timezone":"Africa/Bissau",
    "iso:country":"GW",
    "name:und_x_variant":[
        "Bondjem",
        "Bojandim",
        "Bonjendem"
    ],
    "wof:name":"Bonjendem",
    "wof:placetype":"locality"
},
  "geometry": {"coordinates":[-14.83333,12.06667],"type":"Point"}
}