{
  "type": "Feature",
  "properties": {
    "gn:admin1_code":"00",
    "gn:asciiname":"Imbassina",
    "gn:country_code":"GW",
    "gn:dem":26,
    "gn:feature_class":"P",
    "gn:feature_code":"PPL",
    "gn:name":"Imb\u00e1ssina",
    "gn:population":0,
    "gn:timezone":"Africa/Bissau",
    "iso:country":"GW",
    "wof:name":"Imbassina",
    "wof:placetype":"locality"
},
  "geometry": {"coordinates":[-15.61667,11.93333],"type":"Point"}
}