{
  "type": "Feature",
  "properties": {
    "gn:admin1_code":"00",
    "gn:asciiname":"Mero",
    "gn:country_code":"GW",
    "gn:dem":10,
    "gn:feature_class":"P",
    "gn:feature_code":"PPL",
    "gn:name":"M\u00e9ro",
    "gn:population":0,
    "gn:timezone":"Africa/Bissau",
    "iso:country":"GW",
    "name:ceb_x_preferred":[
        "Mero"
    ],
    "name:deu_x_preferred":[
        "Mero"
    ],
    "name:fra_x_preferred":[
        "M\u00e9ro"
    ],
    "name:glg_x_preferred":[
        "Mero"
    ],
    "name:por_x_preferred":[
        "Mero"
    ],
    "name:swe_x_preferred":[
        "Mero"
    ],
    "wof:name":"Mero",
    "wof:placetype":"locality"
},
  "geometry": {"coordinates":[-14.86667,12.06667],"type":"Point"}
}