{
  "type": "Feature",
  "properties": {
    "gn:admin1_code":"00",
    "gn:asciiname":"Cassina Papel",
    "gn:country_code":"GW",
    "gn:dem":15,
    "gn:feature_class":"P",
    "gn:feature_code":"PPL",
    "gn:name":"C\u00e1ssina Papel",
    "gn:population":0,
    "gn:timezone":"Africa/Bissau",
    "iso:country":"GW",
    "wof:name":"Cassina Papel",
    "wof:placetype":"locality"
},
  "geometry": {"coordinates":[-15.61667,11.86667],"type":"Point"}
}