{
  "type": "Feature",
  "properties": {
    "gn:admin1_code":"06",
    "gn:asciiname":"Quete",
    "gn:country_code":"GW",
    "gn:dem":26,
    "gn:feature_class":"P",
    "gn:feature_code":"PPL",
    "gn:name":"Quete",
    "gn:population":0,
    "gn:timezone":"Africa/Bissau",
    "iso:country":"GW",
    "wof:name":"Quete",
    "wof:placetype":"locality"
},
  "geometry": {"coordinates":[-15.83778,12.12528],"type":"Point"}
}