{
  "type": "Feature",
  "properties": {
    "gn:admin1_code":"04",
    "gn:asciiname":"Enchanque",
    "gn:country_code":"GW",
    "gn:dem":17,
    "gn:feature_class":"P",
    "gn:feature_code":"PPL",
    "gn:name":"Enchanque",
    "gn:population":0,
    "gn:timezone":"Africa/Bissau",
    "iso:country":"GW",
    "wof:name":"Enchanque",
    "wof:placetype":"locality"
},
  "geometry": {"coordinates":[-15.40222,12.07833],"type":"Point"}
}