{
  "type": "Feature",
  "properties": {
    "gn:admin1_code":"00",
    "gn:asciiname":"Nema",
    "gn:country_code":"GW",
    "gn:dem":7,
    "gn:feature_class":"P",
    "gn:feature_code":"PPL",
    "gn:name":"Nema",
    "gn:population":0,
    "gn:timezone":"Africa/Bissau",
    "iso:country":"GW",
    "name:ceb_x_preferred":[
        "Nema"
    ],
    "name:epo_x_preferred":[
        "Nema"
    ],
    "name:fra_x_preferred":[
        "Nema"
    ],
    "name:ita_x_preferred":[
        "Nema"
    ],
    "name:swe_x_preferred":[
        "Nema"
    ],
    "name:tur_x_preferred":[
        "Nema"
    ],
    "wof:name":"Nema",
    "wof:placetype":"locality"
},
  "geometry": {"coordinates":[-14.86667,12.03333],"type":"Point"}
}