{
  "type": "Feature",
  "properties": {
    "gn:admin1_code":"00",
    "gn:asciiname":"Sancorla",
    "gn:country_code":"GW",
    "gn:dem":3,
    "gn:feature_class":"P",
    "gn:feature_code":"PPL",
    "gn:name":"Sancorl\u00e1",
    "gn:population":0,
    "gn:timezone":"Africa/Bissau",
    "iso:country":"GW",
    "wof:name":"Sancorla",
    "wof:placetype":"locality"
},
  "geometry": {"coordinates":[-15.26667,11.83333],"type":"Point"}
}