{
  "type": "Feature",
  "properties": {
    "gn:admin1_code":"04",
    "gn:asciiname":"Nhane",
    "gn:country_code":"GW",
    "gn:dem":15,
    "gn:feature_class":"P",
    "gn:feature_code":"PPL",
    "gn:name":"Nhan\u00e9",
    "gn:population":0,
    "gn:timezone":"Africa/Bissau",
    "iso:country":"GW",
    "wof:name":"Nhane",
    "wof:placetype":"locality"
},
  "geometry": {"coordinates":[-15.40667,12.36083],"type":"Point"}
}