{
  "type": "Feature",
  "properties": {
    "gn:admin1_code":"00",
    "gn:asciiname":"Gandemba",
    "gn:cc2":"GW",
    "gn:country_code":"GW",
    "gn:dem":38,
    "gn:feature_class":"P",
    "gn:feature_code":"PPL",
    "gn:name":"Gandemba",
    "gn:population":0,
    "gn:timezone":"Africa/Bissau",
    "iso:country":"GW",
    "name:und_x_variant":[
        "Dembacunda",
        "Gandemba"
    ],
    "wof:name":"Gandemba",
    "wof:placetype":"locality"
},
  "geometry": {"coordinates":[-14.75,12.16667],"type":"Point"}
}