{
  "type": "Feature",
  "properties": {
    "gn:admin1_code":"00",
    "gn:asciiname":"Ufoia Saje Embalo",
    "gn:country_code":"GW",
    "gn:dem":82,
    "gn:feature_class":"P",
    "gn:feature_code":"PPL",
    "gn:name":"Ufoia Saje Embal\u00f4",
    "gn:population":0,
    "gn:timezone":"Africa/Bissau",
    "iso:country":"GW",
    "wof:name":"Ufoia Saje Embalo",
    "wof:placetype":"locality"
},
  "geometry": {"coordinates":[-14.03333,12.35],"type":"Point"}
}