{
  "type": "Feature",
  "properties": {
    "gn:admin1_code":"04",
    "gn:asciiname":"Ca Mamadu",
    "gn:country_code":"GW",
    "gn:dem":17,
    "gn:feature_class":"P",
    "gn:feature_code":"PPL",
    "gn:name":"C\u00e3 Mamadu",
    "gn:population":0,
    "gn:timezone":"Africa/Bissau",
    "iso:country":"GW",
    "wof:name":"Ca Mamadu",
    "wof:placetype":"locality"
},
  "geometry": {"coordinates":[-15.07417,12.05139],"type":"Point"}
}