{
  "type": "Feature",
  "properties": {
    "gn:admin1_code":"00",
    "gn:asciiname":"Ga Saude",
    "gn:country_code":"GW",
    "gn:dem":16,
    "gn:feature_class":"P",
    "gn:feature_code":"PPL",
    "gn:name":"G\u00e3 Sa\u00fade",
    "gn:population":0,
    "gn:timezone":"Africa/Bissau",
    "iso:country":"GW",
    "wof:name":"Ga Saude",
    "wof:placetype":"locality"
},
  "geometry": {"coordinates":[-15.35,11.73333],"type":"Point"}
}