{
  "type": "Feature",
  "properties": {
    "gn:admin1_code":"00",
    "gn:asciiname":"Sinjanhe",
    "gn:cc2":"GW",
    "gn:country_code":"GW",
    "gn:dem":50,
    "gn:feature_class":"P",
    "gn:feature_code":"PPL",
    "gn:name":"Sinjanhe",
    "gn:population":0,
    "gn:timezone":"Africa/Bissau",
    "iso:country":"GW",
    "name:und_x_variant":[
        "Sinchan",
        "Sinjanhe"
    ],
    "wof:name":"Sinjanhe",
    "wof:placetype":"locality"
},
  "geometry": {"coordinates":[-14.66667,12.03333],"type":"Point"}
}