{
  "type": "Feature",
  "properties": {
    "gn:admin1_code":"00",
    "gn:asciiname":"Bissa",
    "gn:country_code":"GW",
    "gn:dem":6,
    "gn:feature_class":"P",
    "gn:feature_code":"PPL",
    "gn:name":"Bissa",
    "gn:population":0,
    "gn:timezone":"Africa/Bissau",
    "iso:country":"GW",
    "wof:name":"Bissa",
    "wof:placetype":"locality"
},
  "geometry": {"coordinates":[-15.91667,11.85],"type":"Point"}
}