{
  "type": "Feature",
  "properties": {
    "gn:admin1_code":"04",
    "gn:asciiname":"Chile",
    "gn:country_code":"GW",
    "gn:dem":25,
    "gn:feature_class":"P",
    "gn:feature_code":"PPL",
    "gn:name":"Chile",
    "gn:population":0,
    "gn:timezone":"Africa/Bissau",
    "iso:country":"GW",
    "wof:name":"Chile",
    "wof:placetype":"locality"
},
  "geometry": {"coordinates":[-15.67361,12.20389],"type":"Point"}
}