{
  "type": "Feature",
  "properties": {
    "gn:admin1_code":"00",
    "gn:asciiname":"Sare Chumbo",
    "gn:country_code":"GW",
    "gn:dem":21,
    "gn:feature_class":"P",
    "gn:feature_code":"PPL",
    "gn:name":"Sare Chumbo",
    "gn:population":0,
    "gn:timezone":"Africa/Bissau",
    "iso:country":"GW",
    "wof:name":"Sare Chumbo",
    "wof:placetype":"locality"
},
  "geometry": {"coordinates":[-14.55,12.41667],"type":"Point"}
}