{
  "type": "Feature",
  "properties": {
    "gn:admin1_code":"00",
    "gn:asciiname":"Sirael",
    "gn:country_code":"GW",
    "gn:dem":44,
    "gn:feature_class":"P",
    "gn:feature_code":"PPL",
    "gn:name":"Sirael",
    "gn:population":0,
    "gn:timezone":"Africa/Bissau",
    "iso:country":"GW",
    "wof:name":"Sirael",
    "wof:placetype":"locality"
},
  "geometry": {"coordinates":[-14.61667,12.11667],"type":"Point"}
}