{
  "type": "Feature",
  "properties": {
    "gn:admin1_code":"00",
    "gn:asciiname":"Sincha Pate",
    "gn:country_code":"GW",
    "gn:dem":59,
    "gn:feature_class":"P",
    "gn:feature_code":"PPL",
    "gn:name":"Sinch\u00e3 P\u00e1t\u00e8",
    "gn:population":0,
    "gn:timezone":"Africa/Bissau",
    "iso:country":"GW",
    "wof:name":"Sincha Pate",
    "wof:placetype":"locality"
},
  "geometry": {"coordinates":[-14.11667,12.31667],"type":"Point"}
}