{
  "type": "Feature",
  "properties": {
    "gn:admin1_code":"00",
    "gn:asciiname":"Jacunda",
    "gn:country_code":"GW",
    "gn:dem":72,
    "gn:feature_class":"P",
    "gn:feature_code":"PPL",
    "gn:name":"J\u00e1cunda",
    "gn:population":0,
    "gn:timezone":"Africa/Bissau",
    "iso:country":"GW",
    "wof:name":"Jacunda",
    "wof:placetype":"locality"
},
  "geometry": {"coordinates":[-14.13333,12.28333],"type":"Point"}
}