{
  "type": "Feature",
  "properties": {
    "gn:admin1_code":"00",
    "gn:asciiname":"Ponta Benjamim Correia",
    "gn:cc2":"GW",
    "gn:country_code":"GW",
    "gn:dem":24,
    "gn:feature_class":"P",
    "gn:feature_code":"PPL",
    "gn:name":"Ponta Benjamim Correia",
    "gn:population":0,
    "gn:timezone":"Africa/Bissau",
    "iso:country":"GW",
    "name:und_x_variant":[
        "Balanta",
        "Correia",
        "Ponta Benjamim",
        "Ponta Benjamim Correia"
    ],
    "wof:name":"Ponta Benjamim Correia",
    "wof:placetype":"locality"
},
  "geometry": {"coordinates":[-15.71667,11.81667],"type":"Point"}
}