{
  "type": "Feature",
  "properties": {
    "gn:admin1_code":"00",
    "gn:asciiname":"Missira",
    "gn:country_code":"GW",
    "gn:dem":21,
    "gn:feature_class":"P",
    "gn:feature_code":"PPL",
    "gn:name":"Missir\u00e1",
    "gn:population":0,
    "gn:timezone":"Africa/Bissau",
    "iso:country":"GW",
    "name:ceb_x_preferred":[
        "Missira"
    ],
    "name:deu_x_preferred":[
        "Missira"
    ],
    "name:ita_x_preferred":[
        "Missira"
    ],
    "name:spa_x_preferred":[
        "Missira"
    ],
    "name:swe_x_preferred":[
        "Missira"
    ],
    "wof:name":"Missira",
    "wof:placetype":"locality"
},
  "geometry": {"coordinates":[-14.93333,12.28333],"type":"Point"}
}