{
  "type": "Feature",
  "properties": {
    "gn:admin1_code":"00",
    "gn:asciiname":"Ocozinho",
    "gn:cc2":"GW",
    "gn:country_code":"GW",
    "gn:dem":7,
    "gn:feature_class":"P",
    "gn:feature_code":"PPL",
    "gn:name":"Ocozinho",
    "gn:population":0,
    "gn:timezone":"Africa/Bissau",
    "iso:country":"GW",
    "name:und_x_variant":[
        "Oquesinho",
        "Ocozinho"
    ],
    "wof:name":"Ocozinho",
    "wof:placetype":"locality"
},
  "geometry": {"coordinates":[-15.51667,11.95],"type":"Point"}
}