{
  "type": "Feature",
  "properties": {
    "gn:admin1_code":"00",
    "gn:asciiname":"Ponta Honorio",
    "gn:country_code":"GW",
    "gn:dem":6,
    "gn:feature_class":"P",
    "gn:feature_code":"PPL",
    "gn:name":"Ponta Hon\u00f3rio",
    "gn:population":0,
    "gn:timezone":"Africa/Bissau",
    "iso:country":"GW",
    "wof:name":"Ponta Honorio",
    "wof:placetype":"locality"
},
  "geometry": {"coordinates":[-15.83333,11.81667],"type":"Point"}
}