{
  "type": "Feature",
  "properties": {
    "gn:admin1_code":"00",
    "gn:asciiname":"Lenqueteel",
    "gn:cc2":"GW",
    "gn:country_code":"GW",
    "gn:dem":53,
    "gn:feature_class":"P",
    "gn:feature_code":"PPL",
    "gn:name":"Lenqueteel",
    "gn:population":0,
    "gn:timezone":"Africa/Bissau",
    "iso:country":"GW",
    "name:und_x_variant":[
        "Lenqueto",
        "Lenqueteel"
    ],
    "wof:name":"Lenqueteel",
    "wof:placetype":"locality"
},
  "geometry": {"coordinates":[-14.38333,12.35],"type":"Point"}
}