{
  "type": "Feature",
  "properties": {
    "gn:admin1_code":"00",
    "gn:asciiname":"Uaje Fula",
    "gn:cc2":"GW",
    "gn:country_code":"GW",
    "gn:dem":57,
    "gn:feature_class":"P",
    "gn:feature_code":"PPL",
    "gn:name":"Uaj\u00ea Fula",
    "gn:population":0,
    "gn:timezone":"Africa/Bissau",
    "iso:country":"GW",
    "name:und_x_variant":[
        "Uaje Fulbe",
        "Uaj\u00ea Coli",
        "Uaj\u00ea Fula"
    ],
    "wof:name":"Uaje Fula",
    "wof:placetype":"locality"
},
  "geometry": {"coordinates":[-14.61667,12.06667],"type":"Point"}
}