{
  "type": "Feature",
  "properties": {
    "gn:admin1_code":"00",
    "gn:asciiname":"Sare Uale",
    "gn:country_code":"GW",
    "gn:dem":57,
    "gn:feature_class":"P",
    "gn:feature_code":"PPL",
    "gn:name":"Sare Uale",
    "gn:population":0,
    "gn:timezone":"Africa/Bissau",
    "iso:country":"GW",
    "wof:name":"Sare Uale",
    "wof:placetype":"locality"
},
  "geometry": {"coordinates":[-14.61667,12.65],"type":"Point"}
}