{
  "type": "Feature",
  "properties": {
    "gn:elevation":39,
    "iso:country":"GW",
    "name:ara_x_preferred":[
        "\u0645\u0637\u0627\u0631 \u0623\u0648\u0632\u0641\u0627\u0644\u062f\u0648 \u0641\u064a\u064a\u0631\u0627 \u0627\u0644\u062f\u0648\u0644\u064a"
    ],
    "name:cat_x_preferred":[
        "Aeroport Internacional Osvaldo Vieira"
    ],
    "name:chi_x_preferred":[
        "\u5967\u65af\u83ef\u00b7\u6bd4\u827e\u7f85\u6a5f\u5834"
    ],
    "name:dut_x_preferred":[
        "Luchthaven Osvaldo Viera Internationaal"
    ],
    "name:eng_x_preferred":[
        "Bissau Airport"
    ],
    "name:eng_x_variant":[
        "OXB",
        "KOXB",
        "Osvaldo Vieira International Airport"
    ],
    "name:fre_x_preferred":[
        "a\u00e9roport international Osvaldo Vieira de Bissau"
    ],
    "name:ger_x_preferred":[
        "Flughafen Osvaldo Vieira International"
    ],
    "name:hun_x_preferred":[
        "Osvaldo Vieiro nemzetk\u00f6zi rep\u00fcl\u0151t\u00e9r"
    ],
    "name:ind_x_preferred":[
        "Bandar Udara Internasional Osvaldo Vieiro"
    ],
    "name:ita_x_preferred":[
        "Aeroporto di Bissau"
    ],
    "name:jpn_x_preferred":[
        "\u30aa\u30b9\u30f4\u30a1\u30eb\u30c9\u30fb\u30f4\u30a3\u30a8\u30a4\u30e9\u56fd\u969b\u7a7a\u6e2f"
    ],
    "name:lit_x_preferred":[
        "Osvaldo Vieira tarptautinis oro uostas"
    ],
    "name:may_x_preferred":[
        "Lapangan Terbang Osvaldo Vieira"
    ],
    "name:nob_x_preferred":[
        "Osvaldo Vieira internasjonale lufthavn"
    ],
    "name:per_x_preferred":[
        "\u0641\u0631\u0648\u062f\u06af\u0627\u0647 \u0628\u06cc\u0646\u200c\u0627\u0644\u0645\u0644\u0644\u06cc \u0627\u0648\u0633\u0648\u0627\u0644\u062f\u0648 \u0648\u06cc\u06cc\u0631\u0627"
    ],
    "name:pol_x_preferred":[
        "Port lotniczy Bissau"
    ],
    "name:por_x_preferred":[
        "Aeroporto Internacional Osvaldo Vieira"
    ],
    "name:spa_x_preferred":[
        "Aeropuerto Internacional Osvaldo Vieira"
    ],
    "name:swe_x_preferred":[
        "Bissau Aeroport"
    ],
    "name:tgk_x_preferred":[
        "\u0424\u0443\u0440\u0443\u0434\u0433\u043e\u04b3\u0438 \u0431\u0438\u043d\u200c\u0430\u043b\u043c\u0438\u043b\u0430\u043b\u04e3 \u043e\u0432\u0441\u0443\u043e\u043b\u0434\u0443 \u0432\u0438\u0438\u0440\u043e"
    ],
    "name:vie_x_preferred":[
        "S\u00e2n bay qu\u1ed1c t\u1ebf Osvaldo Vieira"
    ],
    "oa:elevation_ft":"129",
    "oa:type":"medium_airport",
    "woe:hierarchy":{
        "country_id":23424929,
        "planet_id":1,
        "state_id":2346610
    },
    "wof:name":"Bissau Oswaldo Vieira Airport",
    "wof:placetype":"campus"
},
  "geometry": {"coordinates":[-15.6537,11.8948],"type":"Point"}
}