{
  "type": "Feature",
  "properties": {
    "gn:admin1_code":"00",
    "gn:asciiname":"Sincha Sambel",
    "gn:country_code":"GW",
    "gn:dem":63,
    "gn:feature_class":"P",
    "gn:feature_code":"PPL",
    "gn:name":"Sinch\u00e3 Sambel",
    "gn:population":0,
    "gn:timezone":"Africa/Bissau",
    "iso:country":"GW",
    "wof:name":"Sincha Sambel",
    "wof:placetype":"locality"
},
  "geometry": {"coordinates":[-14.13333,12.46667],"type":"Point"}
}