{
  "type": "Feature",
  "properties": {
    "gn:admin1_code":"04",
    "gn:asciiname":"Binta",
    "gn:cc2":"GW",
    "gn:country_code":"GW",
    "gn:dem":14,
    "gn:feature_class":"P",
    "gn:feature_code":"PPL",
    "gn:name":"Binta",
    "gn:population":0,
    "gn:timezone":"Africa/Bissau",
    "iso:country":"GW",
    "name:und_x_variant":[
        "Bintam",
        "Binta"
    ],
    "wof:name":"Binta",
    "wof:placetype":"locality"
},
  "geometry": {"coordinates":[-15.31806,12.42028],"type":"Point"}
}