{
  "type": "Feature",
  "properties": {
    "gn:admin1_code":"00",
    "gn:asciiname":"Morocunda",
    "gn:country_code":"GW",
    "gn:dem":12,
    "gn:feature_class":"P",
    "gn:feature_code":"PPL",
    "gn:name":"Morocunda",
    "gn:population":0,
    "gn:timezone":"Africa/Bissau",
    "iso:country":"GW",
    "wof:name":"Morocunda",
    "wof:placetype":"locality"
},
  "geometry": {"coordinates":[-15.21667,12.48333],"type":"Point"}
}