{
  "type": "Feature",
  "properties": {
    "gn:admin1_code":"00",
    "gn:asciiname":"Endorna",
    "gn:country_code":"GW",
    "gn:dem":24,
    "gn:feature_class":"P",
    "gn:feature_code":"PPL",
    "gn:name":"Endorna",
    "gn:population":0,
    "gn:timezone":"Africa/Bissau",
    "iso:country":"GW",
    "wof:name":"Endorna",
    "wof:placetype":"locality"
},
  "geometry": {"coordinates":[-14.83333,11.75],"type":"Point"}
}