{
  "type": "Feature",
  "properties": {
    "gn:admin1_code":"00",
    "gn:asciiname":"Madina Queuto",
    "gn:cc2":"GW",
    "gn:country_code":"GW",
    "gn:dem":38,
    "gn:feature_class":"P",
    "gn:feature_code":"PPL",
    "gn:name":"Madina Qu\u00eauto",
    "gn:population":0,
    "gn:timezone":"Africa/Bissau",
    "iso:country":"GW",
    "name:und_x_variant":[
        "Madina Quento",
        "Madina Qu\u00eauto"
    ],
    "wof:name":"Madina Queuto",
    "wof:placetype":"locality"
},
  "geometry": {"coordinates":[-14.05,12.66667],"type":"Point"}
}