{
  "type": "Feature",
  "properties": {
    "gn:admin1_code":"00",
    "gn:asciiname":"Gamala Jasse",
    "gn:cc2":"GW",
    "gn:country_code":"GW",
    "gn:dem":4,
    "gn:feature_class":"P",
    "gn:feature_code":"PPL",
    "gn:name":"Gamal\u00e3 Jasse",
    "gn:population":0,
    "gn:timezone":"Africa/Bissau",
    "iso:country":"GW",
    "name:und_x_variant":[
        "Candiobe",
        "Gamal\u00e3 Jassi",
        "Gamal\u00e3 Jasse"
    ],
    "wof:name":"Gamala Jasse",
    "wof:placetype":"locality"
},
  "geometry": {"coordinates":[-15.05,11.95],"type":"Point"}
}