{
  "type": "Feature",
  "properties": {
    "gn:admin1_code":"00",
    "gn:asciiname":"Banhima",
    "gn:country_code":"GW",
    "gn:dem":34,
    "gn:feature_class":"P",
    "gn:feature_code":"PPL",
    "gn:name":"Banhima",
    "gn:population":0,
    "gn:timezone":"Africa/Bissau",
    "iso:country":"GW",
    "wof:name":"Banhima",
    "wof:placetype":"locality"
},
  "geometry": {"coordinates":[-15.38333,12.43333],"type":"Point"}
}