{
  "type": "Feature",
  "properties": {
    "gn:admin1_code":"00",
    "gn:asciiname":"Ponta Ponate",
    "gn:country_code":"GW",
    "gn:dem":5,
    "gn:feature_class":"P",
    "gn:feature_code":"PPL",
    "gn:name":"Ponta P\u00f3nate",
    "gn:population":0,
    "gn:timezone":"Africa/Bissau",
    "iso:country":"GW",
    "wof:name":"Ponta Ponate",
    "wof:placetype":"locality"
},
  "geometry": {"coordinates":[-15.75,12.18333],"type":"Point"}
}