{
  "type": "Feature",
  "properties": {
    "gn:admin1_code":"00",
    "gn:asciiname":"Reino de Bijemita",
    "gn:cc2":"GW",
    "gn:country_code":"GW",
    "gn:dem":20,
    "gn:feature_class":"P",
    "gn:feature_code":"PPL",
    "gn:name":"Reino de Bijemita",
    "gn:population":0,
    "gn:timezone":"Africa/Bissau",
    "iso:country":"GW",
    "name:und_x_variant":[
        "Reino",
        "Reino de Bijemita"
    ],
    "wof:name":"Reino de Bijemita",
    "wof:placetype":"locality"
},
  "geometry": {"coordinates":[-15.78333,11.95],"type":"Point"}
}