{
  "type": "Feature",
  "properties": {
    "gn:admin1_code":"00",
    "gn:asciiname":"Manga",
    "gn:country_code":"GW",
    "gn:dem":13,
    "gn:feature_class":"P",
    "gn:feature_code":"PPL",
    "gn:name":"Manga",
    "gn:population":0,
    "gn:timezone":"Africa/Bissau",
    "iso:country":"GW",
    "wof:name":"Manga",
    "wof:placetype":"locality"
},
  "geometry": {"coordinates":[-15.73333,12.03333],"type":"Point"}
}