{
  "type": "Feature",
  "properties": {
    "gn:admin1_code":"06",
    "gn:asciiname":"Betume",
    "gn:country_code":"GW",
    "gn:dem":13,
    "gn:feature_class":"P",
    "gn:feature_code":"PPL",
    "gn:name":"Betume",
    "gn:population":0,
    "gn:timezone":"Africa/Bissau",
    "iso:country":"GW",
    "wof:name":"Betume",
    "wof:placetype":"locality"
},
  "geometry": {"coordinates":[-15.79833,12.04889],"type":"Point"}
}