{
  "type": "Feature",
  "properties": {
    "gn:admin1_code":"00",
    "gn:asciiname":"Uite",
    "gn:country_code":"GW",
    "gn:dem":9,
    "gn:feature_class":"P",
    "gn:feature_code":"PPL",
    "gn:name":"Uite",
    "gn:population":0,
    "gn:timezone":"Africa/Bissau",
    "iso:country":"GW",
    "wof:name":"Uite",
    "wof:placetype":"locality"
},
  "geometry": {"coordinates":[-15.91667,11.05],"type":"Point"}
}