{
  "type": "Feature",
  "properties": {
    "gn:admin1_code":"00",
    "gn:asciiname":"Dinguirai",
    "gn:country_code":"GW",
    "gn:dem":98,
    "gn:feature_class":"P",
    "gn:feature_code":"PPL",
    "gn:name":"Dinguirai",
    "gn:population":0,
    "gn:timezone":"Africa/Bissau",
    "iso:country":"GW",
    "wof:name":"Dinguirai",
    "wof:placetype":"locality"
},
  "geometry": {"coordinates":[-13.86667,11.76667],"type":"Point"}
}