{
  "type": "Feature",
  "properties": {
    "gn:admin1_code":"00",
    "gn:asciiname":"Ga Libra",
    "gn:cc2":"GW",
    "gn:country_code":"GW",
    "gn:dem":5,
    "gn:feature_class":"P",
    "gn:feature_code":"PPL",
    "gn:name":"G\u00e3 Libra",
    "gn:population":0,
    "gn:timezone":"Africa/Bissau",
    "iso:country":"GW",
    "name:und_x_variant":[
        "G\u00e3 Libia",
        "G\u00e3 Libra"
    ],
    "wof:name":"Ga Libra",
    "wof:placetype":"locality"
},
  "geometry": {"coordinates":[-14.85,12.03333],"type":"Point"}
}