{
  "type": "Feature",
  "properties": {
    "gn:admin1_code":"04",
    "gn:asciiname":"Bissora",
    "gn:country_code":"GW",
    "gn:dem":20,
    "gn:feature_class":"P",
    "gn:feature_code":"PPL",
    "gn:name":"Bissor\u00e3",
    "gn:population":0,
    "gn:timezone":"Africa/Bissau",
    "iso:country":"GW",
    "name:und_x_variant":[
        "Bissor\u00e3"
    ],
    "wof:name":"Bissora",
    "wof:placetype":"locality"
},
  "geometry": {"coordinates":[-15.42806,12.04],"type":"Point"}
}