{
  "type": "Feature",
  "properties": {
    "gn:admin1_code":"00",
    "gn:asciiname":"Pontia",
    "gn:country_code":"GW",
    "gn:dem":16,
    "gn:feature_class":"P",
    "gn:feature_code":"PPL",
    "gn:name":"Pontia",
    "gn:population":0,
    "gn:timezone":"Africa/Bissau",
    "iso:country":"GW",
    "name:ast_x_preferred":[
        "Pontia"
    ],
    "name:bul_x_preferred":[
        "Pontia"
    ],
    "name:cat_x_preferred":[
        "Pontia"
    ],
    "name:ceb_x_preferred":[
        "Pontia"
    ],
    "name:fra_x_preferred":[
        "Pontia"
    ],
    "name:nld_x_preferred":[
        "Pontia"
    ],
    "name:nor_x_preferred":[
        "Pontia"
    ],
    "name:rus_x_preferred":[
        "\u041f\u043e\u043d\u0442\u0438\u0438"
    ],
    "name:spa_x_preferred":[
        "Pontia"
    ],
    "name:swe_x_preferred":[
        "Pontia"
    ],
    "name:war_x_preferred":[
        "Pontia"
    ],
    "name:zho_x_preferred":[
        "\u96f2\u7c89\u8776\u5c6c"
    ],
    "wof:name":"Pontia",
    "wof:placetype":"locality"
},
  "geometry": {"coordinates":[-15.58333,11.53333],"type":"Point"}
}