{
  "type": "Feature",
  "properties": {
    "gn:admin1_code":"00",
    "gn:asciiname":"Paunca",
    "gn:country_code":"GW",
    "gn:dem":55,
    "gn:feature_class":"P",
    "gn:feature_code":"PPL",
    "gn:name":"Paunca",
    "gn:population":0,
    "gn:timezone":"Africa/Bissau",
    "iso:country":"GW",
    "wof:name":"Paunca",
    "wof:placetype":"locality"
},
  "geometry": {"coordinates":[-14.28333,12.56667],"type":"Point"}
}