{
  "type": "Feature",
  "properties": {
    "gn:admin1_code":"00",
    "gn:asciiname":"Ca Ierofim",
    "gn:country_code":"GW",
    "gn:dem":46,
    "gn:feature_class":"P",
    "gn:feature_code":"PPL",
    "gn:name":"C\u00e3 Ierofim",
    "gn:population":0,
    "gn:timezone":"Africa/Bissau",
    "iso:country":"GW",
    "wof:name":"Ca Ierofim",
    "wof:placetype":"locality"
},
  "geometry": {"coordinates":[-14.66667,12.33333],"type":"Point"}
}