{
  "type": "Feature",
  "properties": {
    "gn:admin1_code":"00",
    "gn:asciiname":"Canconte",
    "gn:country_code":"GW",
    "gn:dem":27,
    "gn:feature_class":"P",
    "gn:feature_code":"PPL",
    "gn:name":"Cancont\u00e9",
    "gn:population":0,
    "gn:timezone":"Africa/Bissau",
    "iso:country":"GW",
    "wof:name":"Canconte",
    "wof:placetype":"locality"
},
  "geometry": {"coordinates":[-14.85,11.73333],"type":"Point"}
}