{
  "type": "Feature",
  "properties": {
    "gn:admin1_code":"00",
    "gn:asciiname":"Ponta Alfredo Neves",
    "gn:country_code":"GW",
    "gn:dem":40,
    "gn:feature_class":"P",
    "gn:feature_code":"PPL",
    "gn:name":"Ponta Alfredo Neves",
    "gn:population":0,
    "gn:timezone":"Africa/Bissau",
    "iso:country":"GW",
    "wof:name":"Ponta Alfredo Neves",
    "wof:placetype":"locality"
},
  "geometry": {"coordinates":[-15.66667,11.88333],"type":"Point"}
}