{
  "type": "Feature",
  "properties": {
    "gn:admin1_code":"00",
    "gn:asciiname":"Quenheto",
    "gn:cc2":"GW",
    "gn:country_code":"GW",
    "gn:dem":29,
    "gn:feature_class":"P",
    "gn:feature_code":"PPL",
    "gn:name":"Quenhet\u00f3",
    "gn:population":0,
    "gn:timezone":"Africa/Bissau",
    "iso:country":"GW",
    "name:und_x_variant":[
        "Muquejau",
        "Quenhato",
        "Quenhet\u00f3"
    ],
    "wof:name":"Quenheto",
    "wof:placetype":"locality"
},
  "geometry": {"coordinates":[-14.76667,12.11667],"type":"Point"}
}