{
  "type": "Feature",
  "properties": {
    "gn:admin1_code":"06",
    "gn:asciiname":"Sincha Mamadu",
    "gn:country_code":"GW",
    "gn:dem":35,
    "gn:feature_class":"P",
    "gn:feature_code":"PPL",
    "gn:name":"Sinch\u00e3 Mamadu",
    "gn:population":0,
    "gn:timezone":"Africa/Bissau",
    "iso:country":"GW",
    "wof:name":"Sincha Mamadu",
    "wof:placetype":"locality"
},
  "geometry": {"coordinates":[-15.66722,12.40028],"type":"Point"}
}