{
  "type": "Feature",
  "properties": {
    "gn:admin1_code":"04",
    "gn:asciiname":"Iarom",
    "gn:country_code":"GW",
    "gn:dem":32,
    "gn:feature_class":"P",
    "gn:feature_code":"PPL",
    "gn:name":"Iarom",
    "gn:population":0,
    "gn:timezone":"Africa/Bissau",
    "iso:country":"GW",
    "wof:name":"Iarom",
    "wof:placetype":"locality"
},
  "geometry": {"coordinates":[-15.31694,12.23278],"type":"Point"}
}