{
  "type": "Feature",
  "properties": {
    "gn:admin1_code":"06",
    "gn:asciiname":"Pundame",
    "gn:country_code":"GW",
    "gn:dem":25,
    "gn:feature_class":"P",
    "gn:feature_code":"PPL",
    "gn:name":"Pundame",
    "gn:population":0,
    "gn:timezone":"Africa/Bissau",
    "iso:country":"GW",
    "wof:name":"Pundame",
    "wof:placetype":"locality"
},
  "geometry": {"coordinates":[-15.82667,12.30528],"type":"Point"}
}