{
  "type": "Feature",
  "properties": {
    "gn:admin1_code":"00",
    "gn:asciiname":"Cuianca",
    "gn:country_code":"GW",
    "gn:dem":29,
    "gn:feature_class":"P",
    "gn:feature_code":"PPL",
    "gn:name":"Cuianca",
    "gn:population":0,
    "gn:timezone":"Africa/Bissau",
    "iso:country":"GW",
    "wof:name":"Cuianca",
    "wof:placetype":"locality"
},
  "geometry": {"coordinates":[-14.45,12.43333],"type":"Point"}
}