{
  "type": "Feature",
  "properties": {
    "gn:admin1_code":"00",
    "gn:asciiname":"Bila",
    "gn:country_code":"GW",
    "gn:dem":4,
    "gn:feature_class":"P",
    "gn:feature_code":"PPL",
    "gn:name":"Bil\u00e1",
    "gn:population":0,
    "gn:timezone":"Africa/Bissau",
    "iso:country":"GW",
    "name:bos_x_preferred":[
        "Bila"
    ],
    "name:ceb_x_preferred":[
        "Bila"
    ],
    "name:deu_x_preferred":[
        "Bila"
    ],
    "name:est_x_preferred":[
        "Bila"
    ],
    "name:fra_x_preferred":[
        "Bila"
    ],
    "name:hrv_x_preferred":[
        "Bila"
    ],
    "name:ind_x_preferred":[
        "Bila"
    ],
    "name:pol_x_preferred":[
        "Bie\u0142aja"
    ],
    "name:ron_x_preferred":[
        "Bila"
    ],
    "name:slv_x_preferred":[
        "Bila"
    ],
    "name:srp_x_preferred":[
        "\u0411\u0438\u043b\u0430"
    ],
    "name:swe_x_preferred":[
        "Bila"
    ],
    "name:ukr_x_preferred":[
        "\u0411\u0456\u043b\u0430"
    ],
    "wof:name":"Bila",
    "wof:placetype":"locality"
},
  "geometry": {"coordinates":[-15.33333,11.76667],"type":"Point"}
}