{
  "type": "Feature",
  "properties": {
    "gn:admin1_code":"00",
    "gn:asciiname":"Bolama Nova",
    "gn:cc2":"GW",
    "gn:country_code":"GW",
    "gn:dem":30,
    "gn:feature_class":"P",
    "gn:feature_code":"PPL",
    "gn:name":"Bolama Nova",
    "gn:population":0,
    "gn:timezone":"Africa/Bissau",
    "iso:country":"GW",
    "name:und_x_variant":[
        "Bolama Novo",
        "Bolama Nova"
    ],
    "wof:name":"Bolama Nova",
    "wof:placetype":"locality"
},
  "geometry": {"coordinates":[-15.48333,11.58333],"type":"Point"}
}