{
  "type": "Feature",
  "properties": {
    "gn:admin1_code":"06",
    "gn:asciiname":"Campada Bajogate",
    "gn:country_code":"GW",
    "gn:dem":17,
    "gn:feature_class":"P",
    "gn:feature_code":"PPL",
    "gn:name":"Campada Bajogate",
    "gn:population":0,
    "gn:timezone":"Africa/Bissau",
    "iso:country":"GW",
    "wof:name":"Campada Bajogate",
    "wof:placetype":"locality"
},
  "geometry": {"coordinates":[-16.07972,12.42222],"type":"Point"}
}