{
  "type": "Feature",
  "properties": {
    "gn:admin1_code":"00",
    "gn:asciiname":"Darsalame",
    "gn:country_code":"GW",
    "gn:dem":10,
    "gn:feature_class":"P",
    "gn:feature_code":"PPL",
    "gn:name":"Darsalame",
    "gn:population":0,
    "gn:timezone":"Africa/Bissau",
    "iso:country":"GW",
    "wof:name":"Darsalame",
    "wof:placetype":"locality"
},
  "geometry": {"coordinates":[-15.18333,11.18333],"type":"Point"}
}