{
  "type": "Feature",
  "properties": {
    "gn:admin1_code":"00",
    "gn:asciiname":"Sincha Sutu",
    "gn:cc2":"GW",
    "gn:country_code":"GW",
    "gn:dem":41,
    "gn:feature_class":"P",
    "gn:feature_code":"PPL",
    "gn:name":"Sinch\u00e3 Sutu",
    "gn:population":0,
    "gn:timezone":"Africa/Bissau",
    "iso:country":"GW",
    "name:und_x_variant":[
        "Sinch\u00e3 Sulo",
        "Sinch\u00e3 Sutu"
    ],
    "wof:name":"Sincha Sutu",
    "wof:placetype":"locality"
},
  "geometry": {"coordinates":[-14.76667,12.21667],"type":"Point"}
}