{
  "type": "Feature",
  "properties": {
    "gn:admin1_code":"00",
    "gn:asciiname":"Camabe",
    "gn:country_code":"GW",
    "gn:dem":77,
    "gn:feature_class":"P",
    "gn:feature_code":"PPL",
    "gn:name":"Camab\u00e9",
    "gn:population":0,
    "gn:timezone":"Africa/Bissau",
    "iso:country":"GW",
    "wof:name":"Camabe",
    "wof:placetype":"locality"
},
  "geometry": {"coordinates":[-13.88333,12.53333],"type":"Point"}
}