{
  "type": "Feature",
  "properties": {
    "gn:admin1_code":"00",
    "gn:asciiname":"Cabuca",
    "gn:cc2":"GW",
    "gn:country_code":"GW",
    "gn:dem":74,
    "gn:feature_class":"P",
    "gn:feature_code":"PPL",
    "gn:name":"Cabuca",
    "gn:population":0,
    "gn:timezone":"Africa/Bissau",
    "iso:country":"GW",
    "name:und_x_variant":[
        "Caboca",
        "Cabuca"
    ],
    "wof:name":"Cabuca",
    "wof:placetype":"locality"
},
  "geometry": {"coordinates":[-14.05,12.11667],"type":"Point"}
}