{
  "type": "Feature",
  "properties": {
    "gn:admin1_code":"04",
    "gn:asciiname":"Sadejar de Binar",
    "gn:country_code":"GW",
    "gn:dem":26,
    "gn:feature_class":"P",
    "gn:feature_code":"PPL",
    "gn:name":"S\u00e1dejar de Binar",
    "gn:population":0,
    "gn:timezone":"Africa/Bissau",
    "iso:country":"GW",
    "wof:name":"Sadejar de Binar",
    "wof:placetype":"locality"
},
  "geometry": {"coordinates":[-15.6025,12.135],"type":"Point"}
}