{
  "type": "Feature",
  "properties": {
    "gn:admin1_code":"00",
    "gn:asciiname":"Sincha Capassa",
    "gn:country_code":"GW",
    "gn:dem":52,
    "gn:feature_class":"P",
    "gn:feature_code":"PPL",
    "gn:name":"Sinch\u00e3 Capassa",
    "gn:population":0,
    "gn:timezone":"Africa/Bissau",
    "iso:country":"GW",
    "wof:name":"Sincha Capassa",
    "wof:placetype":"locality"
},
  "geometry": {"coordinates":[-13.95,12.36667],"type":"Point"}
}