{
  "type": "Feature",
  "properties": {
    "gn:admin1_code":"00",
    "gn:asciiname":"Ponta Doce",
    "gn:country_code":"GW",
    "gn:dem":37,
    "gn:feature_class":"P",
    "gn:feature_code":"PPL",
    "gn:name":"Ponta Doce",
    "gn:population":0,
    "gn:timezone":"Africa/Bissau",
    "iso:country":"GW",
    "wof:name":"Ponta Doce",
    "wof:placetype":"locality"
},
  "geometry": {"coordinates":[-15.25,12.53333],"type":"Point"}
}