{
  "type": "Feature",
  "properties": {
    "gn:admin1_code":"04",
    "gn:asciiname":"Cussanja",
    "gn:country_code":"GW",
    "gn:dem":16,
    "gn:feature_class":"P",
    "gn:feature_code":"PPL",
    "gn:name":"Cussanja",
    "gn:population":0,
    "gn:timezone":"Africa/Bissau",
    "iso:country":"GW",
    "wof:name":"Cussanja",
    "wof:placetype":"locality"
},
  "geometry": {"coordinates":[-15.28833,12.04722],"type":"Point"}
}