{
  "type": "Feature",
  "properties": {
    "gn:admin1_code":"00",
    "gn:asciiname":"Cassaca",
    "gn:cc2":"GW",
    "gn:country_code":"GW",
    "gn:dem":6,
    "gn:feature_class":"P",
    "gn:feature_code":"PPL",
    "gn:name":"Cassaca",
    "gn:population":0,
    "gn:timezone":"Africa/Bissau",
    "iso:country":"GW",
    "name:und_x_variant":[
        "Cassag\u00e1",
        "Cassaca"
    ],
    "wof:name":"Cassaca",
    "wof:placetype":"locality"
},
  "geometry": {"coordinates":[-16.13332999999999,11.86667],"type":"Point"}
}