{
  "type": "Feature",
  "properties": {
    "gn:admin1_code":"00",
    "gn:asciiname":"Encheia",
    "gn:country_code":"GW",
    "gn:dem":13,
    "gn:feature_class":"P",
    "gn:feature_code":"PPL",
    "gn:name":"Encheia",
    "gn:population":0,
    "gn:timezone":"Africa/Bissau",
    "iso:country":"GW",
    "wof:name":"Encheia",
    "wof:placetype":"locality"
},
  "geometry": {"coordinates":[-15.56667,12.33333],"type":"Point"}
}