{
  "type": "Feature",
  "properties": {
    "gn:admin1_code":"00",
    "gn:asciiname":"Sincha Bala",
    "gn:country_code":"GW",
    "gn:dem":70,
    "gn:feature_class":"P",
    "gn:feature_code":"PPL",
    "gn:name":"Sinch\u00e3 B\u00e1l\u00e0",
    "gn:population":0,
    "gn:timezone":"Africa/Bissau",
    "iso:country":"GW",
    "wof:name":"Sincha Bala",
    "wof:placetype":"locality"
},
  "geometry": {"coordinates":[-14.25,12.36667],"type":"Point"}
}