{
  "type": "Feature",
  "properties": {
    "gn:admin1_code":"00",
    "gn:asciiname":"Dutequete",
    "gn:country_code":"GW",
    "gn:dem":19,
    "gn:feature_class":"P",
    "gn:feature_code":"PPL",
    "gn:name":"Dutequete",
    "gn:population":0,
    "gn:timezone":"Africa/Bissau",
    "iso:country":"GW",
    "wof:name":"Dutequete",
    "wof:placetype":"locality"
},
  "geometry": {"coordinates":[-15.83333,12.11667],"type":"Point"}
}