{
  "type": "Feature",
  "properties": {
    "gn:admin1_code":"04",
    "gn:asciiname":"Matar",
    "gn:country_code":"GW",
    "gn:dem":15,
    "gn:feature_class":"P",
    "gn:feature_code":"PPL",
    "gn:name":"Matar",
    "gn:population":0,
    "gn:timezone":"Africa/Bissau",
    "iso:country":"GW",
    "wof:name":"Matar",
    "wof:placetype":"locality"
},
  "geometry": {"coordinates":[-15.50889,12.34556],"type":"Point"}
}