{
  "type": "Feature",
  "properties": {
    "gn:admin1_code":"00",
    "gn:asciiname":"Cantassia",
    "gn:cc2":"GW",
    "gn:country_code":"GW",
    "gn:dem":50,
    "gn:feature_class":"P",
    "gn:feature_code":"PPL",
    "gn:name":"Cant\u00e1ssi\u00e0",
    "gn:population":0,
    "gn:timezone":"Africa/Bissau",
    "iso:country":"GW",
    "name:und_x_variant":[
        "Contassi\u00e1",
        "Cant\u00e1ssi\u00e0"
    ],
    "wof:name":"Cantassia",
    "wof:placetype":"locality"
},
  "geometry": {"coordinates":[-14.28333,11.73333],"type":"Point"}
}