{
  "type": "Feature",
  "properties": {
    "gn:admin1_code":"00",
    "gn:asciiname":"Cancubanhe Maunde",
    "gn:country_code":"GW",
    "gn:dem":44,
    "gn:feature_class":"P",
    "gn:feature_code":"PPL",
    "gn:name":"Cancubanhe Maund\u00e8",
    "gn:population":0,
    "gn:timezone":"Africa/Bissau",
    "iso:country":"GW",
    "wof:name":"Cancubanhe Maunde",
    "wof:placetype":"locality"
},
  "geometry": {"coordinates":[-14.75,12.48333],"type":"Point"}
}