{
  "type": "Feature",
  "properties": {
    "gn:admin1_code":"00",
    "gn:asciiname":"Cambeque",
    "gn:cc2":"GW",
    "gn:country_code":"GW",
    "gn:dem":14,
    "gn:feature_class":"P",
    "gn:feature_code":"PPL",
    "gn:name":"Cambeque",
    "gn:population":0,
    "gn:timezone":"Africa/Bissau",
    "iso:country":"GW",
    "name:und_x_variant":[
        "Cambegue",
        "Cambeque"
    ],
    "wof:name":"Cambeque",
    "wof:placetype":"locality"
},
  "geometry": {"coordinates":[-15.03333,11.18333],"type":"Point"}
}