{
  "type": "Feature",
  "properties": {
    "gn:admin1_code":"00",
    "gn:asciiname":"Capunga",
    "gn:country_code":"GW",
    "gn:dem":32,
    "gn:feature_class":"P",
    "gn:feature_code":"PPL",
    "gn:name":"Capunga",
    "gn:population":0,
    "gn:timezone":"Africa/Bissau",
    "iso:country":"GW",
    "wof:name":"Capunga",
    "wof:placetype":"locality"
},
  "geometry": {"coordinates":[-15.68333,12.11667],"type":"Point"}
}