{
  "type": "Feature",
  "properties": {
    "gn:admin1_code":"00",
    "gn:asciiname":"Doum Eta",
    "gn:country_code":"GW",
    "gn:dem":58,
    "gn:feature_class":"P",
    "gn:feature_code":"PPL",
    "gn:name":"Doum Eta",
    "gn:population":0,
    "gn:timezone":"Africa/Bissau",
    "iso:country":"GW",
    "wof:name":"Doum Eta",
    "wof:placetype":"locality"
},
  "geometry": {"coordinates":[-13.66667,12.31667],"type":"Point"}
}