{
  "type": "Feature",
  "properties": {
    "gn:admin1_code":"00",
    "gn:asciiname":"Ganha Balanta",
    "gn:country_code":"GW",
    "gn:dem":8,
    "gn:feature_class":"P",
    "gn:feature_code":"PPL",
    "gn:name":"Ganh\u00e0 Balanta",
    "gn:population":0,
    "gn:timezone":"Africa/Bissau",
    "iso:country":"GW",
    "wof:name":"Ganha Balanta",
    "wof:placetype":"locality"
},
  "geometry": {"coordinates":[-14.85,11.75],"type":"Point"}
}