{
  "type": "Feature",
  "properties": {
    "gn:admin1_code":"00",
    "gn:asciiname":"Tendeiro",
    "gn:country_code":"GW",
    "gn:dem":76,
    "gn:feature_class":"P",
    "gn:feature_code":"PPL",
    "gn:name":"Tendeiro",
    "gn:population":0,
    "gn:timezone":"Africa/Bissau",
    "iso:country":"GW",
    "wof:name":"Tendeiro",
    "wof:placetype":"locality"
},
  "geometry": {"coordinates":[-13.65,12.46667],"type":"Point"}
}