{
  "type": "Feature",
  "properties": {
    "gn:admin1_code":"00",
    "gn:asciiname":"Madina Cabonepo",
    "gn:country_code":"GW",
    "gn:dem":16,
    "gn:feature_class":"P",
    "gn:feature_code":"PPL",
    "gn:name":"Madina Cabonepo",
    "gn:population":0,
    "gn:timezone":"Africa/Bissau",
    "iso:country":"GW",
    "wof:name":"Madina Cabonepo",
    "wof:placetype":"locality"
},
  "geometry": {"coordinates":[-15.03333,11.05],"type":"Point"}
}