{
  "type": "Feature",
  "properties": {
    "gn:admin1_code":"00",
    "gn:asciiname":"Cheque",
    "gn:country_code":"GW",
    "gn:dem":15,
    "gn:feature_class":"P",
    "gn:feature_code":"PPL",
    "gn:name":"Cheque",
    "gn:population":0,
    "gn:timezone":"Africa/Bissau",
    "iso:country":"GW",
    "wof:name":"Cheque",
    "wof:placetype":"locality"
},
  "geometry": {"coordinates":[-14.63333,12.15],"type":"Point"}
}