{
  "type": "Feature",
  "properties": {
    "gn:admin1_code":"06",
    "gn:asciiname":"Canjinha",
    "gn:cc2":"GW",
    "gn:country_code":"GW",
    "gn:dem":37,
    "gn:feature_class":"P",
    "gn:feature_code":"PPL",
    "gn:name":"Canjinha",
    "gn:population":0,
    "gn:timezone":"Africa/Bissau",
    "iso:country":"GW",
    "name:und_x_variant":[
        "Canja",
        "Canjinha"
    ],
    "wof:name":"Canjinha",
    "wof:placetype":"locality"
},
  "geometry": {"coordinates":[-15.70611,12.39278],"type":"Point"}
}