{
  "type": "Feature",
  "properties": {
    "gn:admin1_code":"04",
    "gn:asciiname":"Ca Cumba",
    "gn:country_code":"GW",
    "gn:dem":25,
    "gn:feature_class":"P",
    "gn:feature_code":"PPL",
    "gn:name":"C\u00e3 Cumba",
    "gn:population":0,
    "gn:timezone":"Africa/Bissau",
    "iso:country":"GW",
    "wof:name":"Ca Cumba",
    "wof:placetype":"locality"
},
  "geometry": {"coordinates":[-15.06056,12.24194],"type":"Point"}
}