{
  "type": "Feature",
  "properties": {
    "gn:admin1_code":"06",
    "gn:asciiname":"Bajique",
    "gn:country_code":"GW",
    "gn:dem":35,
    "gn:feature_class":"P",
    "gn:feature_code":"PPL",
    "gn:name":"Bajique",
    "gn:population":0,
    "gn:timezone":"Africa/Bissau",
    "iso:country":"GW",
    "wof:name":"Bajique",
    "wof:placetype":"locality"
},
  "geometry": {"coordinates":[-15.83806,12.09083],"type":"Point"}
}