{
  "type": "Feature",
  "properties": {
    "gn:admin1_code":"00",
    "gn:asciiname":"Sare Morija",
    "gn:country_code":"GW",
    "gn:dem":46,
    "gn:feature_class":"P",
    "gn:feature_code":"PPL",
    "gn:name":"Sare Morij\u00e3",
    "gn:population":0,
    "gn:timezone":"Africa/Bissau",
    "iso:country":"GW",
    "wof:name":"Sare Morija",
    "wof:placetype":"locality"
},
  "geometry": {"coordinates":[-14.95,12.46667],"type":"Point"}
}