{
  "type": "Feature",
  "properties": {
    "gn:admin1_code":"00",
    "gn:asciiname":"Bulel Samba",
    "gn:cc2":"GW",
    "gn:country_code":"GW",
    "gn:dem":12,
    "gn:feature_class":"P",
    "gn:feature_code":"PPL",
    "gn:name":"Bulel Samba",
    "gn:population":0,
    "gn:timezone":"Africa/Bissau",
    "iso:country":"GW",
    "name:und_x_variant":[
        "Bolel Samba",
        "Bulel Samba"
    ],
    "wof:name":"Bulel Samba",
    "wof:placetype":"locality"
},
  "geometry": {"coordinates":[-15.06667,11.45],"type":"Point"}
}