{
  "type": "Feature",
  "properties": {
    "gn:admin1_code":"00",
    "gn:asciiname":"Samene",
    "gn:country_code":"GW",
    "gn:dem":2,
    "gn:feature_class":"P",
    "gn:feature_code":"PPL",
    "gn:name":"S\u00e2mene",
    "gn:population":0,
    "gn:timezone":"Africa/Bissau",
    "iso:country":"GW",
    "wof:name":"Samene",
    "wof:placetype":"locality"
},
  "geometry": {"coordinates":[-15.81667,12.41667],"type":"Point"}
}