{
  "type": "Feature",
  "properties": {
    "gn:admin1_code":"00",
    "gn:asciiname":"Sincha Dulo",
    "gn:country_code":"GW",
    "gn:dem":27,
    "gn:feature_class":"P",
    "gn:feature_code":"PPL",
    "gn:name":"Sinch\u00e3 Dulo",
    "gn:population":0,
    "gn:timezone":"Africa/Bissau",
    "iso:country":"GW",
    "wof:name":"Sincha Dulo",
    "wof:placetype":"locality"
},
  "geometry": {"coordinates":[-14.66667,12.18333],"type":"Point"}
}