{
  "type": "Feature",
  "properties": {
    "gn:admin1_code":"00",
    "gn:asciiname":"Gambana",
    "gn:country_code":"GW",
    "gn:dem":21,
    "gn:feature_class":"P",
    "gn:feature_code":"PPL",
    "gn:name":"Gamban\u00e1",
    "gn:population":0,
    "gn:timezone":"Africa/Bissau",
    "iso:country":"GW",
    "wof:name":"Gambana",
    "wof:placetype":"locality"
},
  "geometry": {"coordinates":[-15.08333,11.91667],"type":"Point"}
}