{
  "type": "Feature",
  "properties": {
    "gn:admin1_code":"04",
    "gn:asciiname":"Camalem",
    "gn:cc2":"GW",
    "gn:country_code":"GW",
    "gn:dem":38,
    "gn:feature_class":"P",
    "gn:feature_code":"PPL",
    "gn:name":"Camalem",
    "gn:population":0,
    "gn:timezone":"Africa/Bissau",
    "iso:country":"GW",
    "name:und_x_variant":[
        "Camelem",
        "Camalem"
    ],
    "wof:name":"Camalem",
    "wof:placetype":"locality"
},
  "geometry": {"coordinates":[-15.0225,12.52333],"type":"Point"}
}