{
  "type": "Feature",
  "properties": {
    "gn:admin1_code":"06",
    "gn:asciiname":"Cassa",
    "gn:country_code":"GW",
    "gn:dem":33,
    "gn:feature_class":"P",
    "gn:feature_code":"PPL",
    "gn:name":"Cass\u00e0",
    "gn:population":0,
    "gn:timezone":"Africa/Bissau",
    "iso:country":"GW",
    "wof:name":"Cassa",
    "wof:placetype":"locality"
},
  "geometry": {"coordinates":[-15.75083,12.06528],"type":"Point"}
}