{
  "type": "Feature",
  "properties": {
    "gn:admin1_code":"00",
    "gn:asciiname":"Jaribe",
    "gn:cc2":"GW",
    "gn:country_code":"GW",
    "gn:dem":62,
    "gn:feature_class":"P",
    "gn:feature_code":"PPL",
    "gn:name":"Jaribe",
    "gn:population":0,
    "gn:timezone":"Africa/Bissau",
    "iso:country":"GW",
    "name:und_x_variant":[
        "Jerib\u00e9",
        "Jaribe"
    ],
    "wof:name":"Jaribe",
    "wof:placetype":"locality"
},
  "geometry": {"coordinates":[-14.18333,11.68333],"type":"Point"}
}