{
  "type": "Feature",
  "properties": {
    "gn:admin1_code":"04",
    "gn:asciiname":"Norobanta Mandinga",
    "gn:country_code":"GW",
    "gn:dem":36,
    "gn:feature_class":"P",
    "gn:feature_code":"PPL",
    "gn:name":"Norobanta Mandinga",
    "gn:population":0,
    "gn:timezone":"Africa/Bissau",
    "iso:country":"GW",
    "wof:name":"Norobanta Mandinga",
    "wof:placetype":"locality"
},
  "geometry": {"coordinates":[-15.06694,12.62444],"type":"Point"}
}