{
  "type": "Feature",
  "properties": {
    "gn:admin1_code":"04",
    "gn:asciiname":"Maninha",
    "gn:country_code":"GW",
    "gn:dem":22,
    "gn:feature_class":"P",
    "gn:feature_code":"PPL",
    "gn:name":"Maninh\u00e3",
    "gn:population":0,
    "gn:timezone":"Africa/Bissau",
    "iso:country":"GW",
    "wof:name":"Maninha",
    "wof:placetype":"locality"
},
  "geometry": {"coordinates":[-15.08639,12.4475],"type":"Point"}
}