{
  "type": "Feature",
  "properties": {
    "gn:admin1_code":"06",
    "gn:asciiname":"Begundo",
    "gn:country_code":"GW",
    "gn:dem":13,
    "gn:feature_class":"P",
    "gn:feature_code":"PPL",
    "gn:name":"Begundo",
    "gn:population":0,
    "gn:timezone":"Africa/Bissau",
    "iso:country":"GW",
    "wof:name":"Begundo",
    "wof:placetype":"locality"
},
  "geometry": {"coordinates":[-16.15972,12.37167],"type":"Point"}
}