{
  "type": "Feature",
  "properties": {
    "gn:admin1_code":"06",
    "gn:asciiname":"Pepantar",
    "gn:cc2":"GW",
    "gn:country_code":"GW",
    "gn:dem":15,
    "gn:feature_class":"P",
    "gn:feature_code":"PPL",
    "gn:name":"Pepantar",
    "gn:population":0,
    "gn:timezone":"Africa/Bissau",
    "iso:country":"GW",
    "name:und_x_variant":[
        "Ponta Vicente",
        "Pepantar"
    ],
    "wof:name":"Pepantar",
    "wof:placetype":"locality"
},
  "geometry": {"coordinates":[-15.90778,12.21833],"type":"Point"}
}