{
  "type": "Feature",
  "properties": {
    "gn:admin1_code":"00",
    "gn:asciiname":"Culobo",
    "gn:cc2":"GW",
    "gn:country_code":"GW",
    "gn:dem":33,
    "gn:feature_class":"P",
    "gn:feature_code":"PPL",
    "gn:name":"Cul\u00f4bo",
    "gn:population":0,
    "gn:timezone":"Africa/Bissau",
    "iso:country":"GW",
    "name:und_x_variant":[
        "Jagaraja",
        "Colobo",
        "Cul\u00f4bo"
    ],
    "wof:name":"Culobo",
    "wof:placetype":"locality"
},
  "geometry": {"coordinates":[-14.81667,11.78333],"type":"Point"}
}