{
  "type": "Feature",
  "properties": {
    "gn:admin1_code":"00",
    "gn:asciiname":"Inorei",
    "gn:country_code":"GW",
    "gn:dem":8,
    "gn:feature_class":"P",
    "gn:feature_code":"PPL",
    "gn:name":"Inorei",
    "gn:population":0,
    "gn:timezone":"Africa/Bissau",
    "iso:country":"GW",
    "wof:name":"Inorei",
    "wof:placetype":"locality"
},
  "geometry": {"coordinates":[-15.67204,11.29605],"type":"Point"}
}