{
  "type": "Feature",
  "properties": {
    "gn:admin1_code":"00",
    "gn:asciiname":"Bandim",
    "gn:country_code":"GW",
    "gn:dem":5,
    "gn:feature_class":"P",
    "gn:feature_code":"PPL",
    "gn:name":"Bandim",
    "gn:population":0,
    "gn:timezone":"Africa/Bissau",
    "iso:country":"GW",
    "wof:name":"Bandim",
    "wof:placetype":"locality"
},
  "geometry": {"coordinates":[-15.38333,11.33333],"type":"Point"}
}