{
  "type": "Feature",
  "properties": {
    "gn:admin1_code":"00",
    "gn:asciiname":"Uelingara",
    "gn:country_code":"GW",
    "gn:dem":32,
    "gn:feature_class":"P",
    "gn:feature_code":"PPL",
    "gn:name":"Uel\u00edngar\u00e0",
    "gn:population":0,
    "gn:timezone":"Africa/Bissau",
    "iso:country":"GW",
    "wof:name":"Uelingara",
    "wof:placetype":"locality"
},
  "geometry": {"coordinates":[-14.56667,12.48333],"type":"Point"}
}