{
  "type": "Feature",
  "properties": {
    "gn:admin1_code":"06",
    "gn:asciiname":"Igim",
    "gn:cc2":"GW",
    "gn:country_code":"GW",
    "gn:dem":8,
    "gn:feature_class":"P",
    "gn:feature_code":"PPL",
    "gn:name":"Igim",
    "gn:population":0,
    "gn:timezone":"Africa/Bissau",
    "iso:country":"GW",
    "name:und_x_variant":[
        "Egine",
        "Igim"
    ],
    "wof:name":"Igim",
    "wof:placetype":"locality"
},
  "geometry": {"coordinates":[-16.46944,12.23056],"type":"Point"}
}