{
  "type": "Feature",
  "properties": {
    "gn:admin1_code":"00",
    "gn:asciiname":"Mareue",
    "gn:cc2":"GW",
    "gn:country_code":"GW",
    "gn:dem":50,
    "gn:feature_class":"P",
    "gn:feature_code":"PPL",
    "gn:name":"Mar\u00e9u\u00e8",
    "gn:population":0,
    "gn:timezone":"Africa/Bissau",
    "iso:country":"GW",
    "name:und_x_variant":[
        "Maren\u00e9",
        "Mar\u00e9u\u00e8"
    ],
    "wof:name":"Mareue",
    "wof:placetype":"locality"
},
  "geometry": {"coordinates":[-14.13333,12.51667],"type":"Point"}
}