{
  "type": "Feature",
  "properties": {
    "gn:admin1_code":"00",
    "gn:asciiname":"Bambadinca",
    "gn:country_code":"GW",
    "gn:dem":55,
    "gn:feature_class":"P",
    "gn:feature_code":"PPL",
    "gn:name":"Bambadinca",
    "gn:population":0,
    "gn:timezone":"Africa/Bissau",
    "iso:country":"GW",
    "name:cat_x_preferred":[
        "Bambadinca"
    ],
    "name:ceb_x_preferred":[
        "Bambadinca"
    ],
    "name:deu_x_preferred":[
        "Bambadinca"
    ],
    "name:fin_x_preferred":[
        "Bambadinca"
    ],
    "name:fra_x_preferred":[
        "Bambadinca"
    ],
    "name:ita_x_preferred":[
        "Bambadinca"
    ],
    "name:jpn_x_preferred":[
        "\u30d0\u30f3\u30d0\u30c7\u30a3\u30f3\u30ab"
    ],
    "name:por_x_preferred":[
        "Bambadinca"
    ],
    "name:swe_x_preferred":[
        "Bambadinca"
    ],
    "name:ukr_x_preferred":[
        "\u0411\u0430\u043c\u0431\u0430\u0434\u0456\u043d\u0441\u0430"
    ],
    "wof:name":"Bambadinca",
    "wof:placetype":"locality"
},
  "geometry": {"coordinates":[-14.48333,12.16667],"type":"Point"}
}