{
  "type": "Feature",
  "properties": {
    "gn:admin1_code":"00",
    "gn:asciiname":"Bacar Julere",
    "gn:country_code":"GW",
    "gn:dem":67,
    "gn:feature_class":"P",
    "gn:feature_code":"PPL",
    "gn:name":"B\u00e1car J\u00faler\u00e8",
    "gn:population":0,
    "gn:timezone":"Africa/Bissau",
    "iso:country":"GW",
    "wof:name":"Bacar Julere",
    "wof:placetype":"locality"
},
  "geometry": {"coordinates":[-14.01667,12.28333],"type":"Point"}
}