{
  "type": "Feature",
  "properties": {
    "gn:admin1_code":"00",
    "gn:asciiname":"Sincha Nhinha",
    "gn:country_code":"GW",
    "gn:dem":31,
    "gn:feature_class":"P",
    "gn:feature_code":"PPL",
    "gn:name":"Sinch\u00e3 Nhinha",
    "gn:population":0,
    "gn:timezone":"Africa/Bissau",
    "iso:country":"GW",
    "wof:name":"Sincha Nhinha",
    "wof:placetype":"locality"
},
  "geometry": {"coordinates":[-14.43333,12.38333],"type":"Point"}
}